{
  "questions": [
    {
      "correct_answer": "A",
      "options": [
        {
          "id": "A",
          "text": "₹4914.55"
        },
        {
          "id": "B",
          "text": "₹4714.55"
        },
        {
          "id": "C",
          "text": "₹4614.55"
        },
        {
          "id": "D",
          "text": "₹4814.55"
        }
      ],
      "question_number": 1,
      "question_text": "A sum of money amounts to ₹19,360 in 3 years at 10% per annum, compounded annually. The compound interest (in ₹) earned is (Round off your answer to the nearest paise).",
      "exam_type": "RRB",
      "sub_type": "RRB (NTPC)"
    },
    {
      "correct_answer": "B",
      "options": [
        {
          "id": "A",
          "text": "132 minutes"
        },
        {
          "id": "B",
          "text": "126 minutes"
        },
        {
          "id": "C",
          "text": "142 minutes"
        },
        {
          "id": "D",
          "text": "136 minutes"
        }
      ],
      "question_number": 2,
      "question_text": "Three automatic doors in a metro station undergo system checks at regular intervals of 14 minutes, 18 minutes, and 21 minutes, respectively. If all three doors are checked together at the start, after how many minutes will they be checked together again for the first time?",
      "exam_type": "RRB",
      "sub_type": "RRB (NTPC)"
    },
    {
      "correct_answer": "A",
      "options": [
        {
          "id": "A",
          "text": "Aman: ₹6,000, Raj: ₹9,000"
        },
        {
          "id": "B",
          "text": "Aman: ₹7,500, Raj: ₹7,500"
        },
        {
          "id": "C",
          "text": "Aman: ₹5,000, Raj: ₹9,000"
        },
        {
          "id": "D",
          "text": "Aman: ₹5,000, Raj: ₹10,000"
        }
      ],
      "question_number": 3,
      "question_text": "Aman and Raj invested ₹12,000 and ₹18,000, respectively, in a business. After one year, they earned a profit of ₹15,000. How much profit will each get?",
      "exam_type": "RRB",
      "sub_type": "RRB (NTPC)"
    },
    {
      "correct_answer": "D",
      "options": [
        {
          "id": "A",
          "text": "$28\\sqrt{3}$ km/h"
        },
        {
          "id": "B",
          "text": "$30\\sqrt{2}$ km/h"
        },
        {
          "id": "C",
          "text": "$28\\sqrt{2}$ km/h"
        },
        {
          "id": "D",
          "text": "$30\\sqrt{3}$ km/h"
        }
      ],
      "question_number": 4,
      "question_text": "Two trains, X and Y, start at the same time from Delhi and Mumbai towards each other. After meeting, train X takes 6 hours to reach Mumbai, and train Y takes 8 hours to reach Delhi. If train X's speed is 60 km/h, what is the speed of train Y?",
      "exam_type": "RRB",
      "sub_type": "RRB (NTPC)"
    },
    {
      "correct_answer": "C",
      "options": [
        {
          "id": "A",
          "text": "$3\\sqrt{2}$"
        },
        {
          "id": "B",
          "text": "$\\sqrt{3}$"
        },
        {
          "id": "C",
          "text": "$2\\sqrt{3}$"
        },
        {
          "id": "D",
          "text": "$5\\sqrt{3}$"
        }
      ],
      "question_number": 5,
      "question_text": "The value of $(\\cos^2 67^\\circ - \\sin^2 23^\\circ) + 4 \\cos 30^\\circ$ is:",
      "exam_type": "RRB",
      "sub_type": "RRB (NTPC)"
    },
    {
      "correct_answer": "A",
      "options": [
        {
          "id": "A",
          "text": "20.73"
        },
        {
          "id": "B",
          "text": "21.23"
        },
        {
          "id": "C",
          "text": "19.85"
        },
        {
          "id": "D",
          "text": "26.48"
        }
      ],
      "question_number": 6,
      "question_text": "Find the median of the following data (correct to two places of decimal).Class Interval 0-6 6-12 12-18 18-24 24-30 30-36Frequency 5 7 10 13 9 8",
      "exam_type": "RRB",
      "sub_type": "RRB (NTPC)"
    },
    {
      "correct_answer": "A",
      "options": [
        {
          "id": "A",
          "text": "16,94,000"
        },
        {
          "id": "B",
          "text": "16,74,000"
        },
        {
          "id": "C",
          "text": "16,64,000"
        },
        {
          "id": "D",
          "text": "16,84,000"
        }
      ],
      "question_number": 7,
      "question_text": "A cylindrical tank has a radius of 7 m and a height of 11 m. How many litres of water can it hold? (Use $\\pi = 22/7$)",
      "exam_type": "RRB",
      "sub_type": "RRB (NTPC)"
    },
    {
      "correct_answer": "C",
      "options": [
        {
          "id": "A",
          "text": "₹960"
        },
        {
          "id": "B",
          "text": "₹1,050"
        },
        {
          "id": "C",
          "text": "₹840"
        },
        {
          "id": "D",
          "text": "₹1,100"
        }
      ],
      "question_number": 8,
      "question_text": "A shopkeeper bought 7 decorative lamps for ₹2,450. Due to damage, 2 lamps could not be sold. He sold the remaining lamps at ₹360 each. What is his total loss (in ₹)?",
      "exam_type": "RRB",
      "sub_type": "RRB (NTPC)"
    },
    {
      "correct_answer": "C",
      "options": [
        {
          "id": "A",
          "text": "₹9,800"
        },
        {
          "id": "B",
          "text": "₹9,400"
        },
        {
          "id": "C",
          "text": "₹10,000"
        },
        {
          "id": "D",
          "text": "₹9,600"
        }
      ],
      "question_number": 9,
      "question_text": "The cost of a certain fabric is directly proportional to its length for a given width. If the cost of 8 meters of the fabric is ₹3,200, what will be the cost of 25 meters of the same fabric?",
      "exam_type": "RRB",
      "sub_type": "RRB (NTPC)"
    },
    {
      "correct_answer": "A",
      "options": [
        {
          "id": "A",
          "text": "29"
        },
        {
          "id": "B",
          "text": "30"
        },
        {
          "id": "C",
          "text": "28"
        },
        {
          "id": "D",
          "text": "26"
        }
      ],
      "question_number": 10,
      "question_text": "Find the mode of the following distribution:Class 5-15 15-25 25-35 35-45Frequency 6 14 18 12",
      "exam_type": "RRB",
      "sub_type": "RRB (NTPC)"
    },
    {
      "correct_answer": "D",
      "options": [
        {
          "id": "A",
          "text": "15"
        },
        {
          "id": "B",
          "text": "18"
        },
        {
          "id": "C",
          "text": "22"
        },
        {
          "id": "D",
          "text": "20"
        }
      ],
      "question_number": 11,
      "question_text": "40 persons begin to work together on a job. But after some days 10 persons left the work. If the work, that would have been completed in 40 days, completed in 50 days. How many days after the commencement of the work did the 10 persons leave?",
      "exam_type": "RRB",
      "sub_type": "RRB (NTPC)"
    },
    {
      "correct_answer": "B",
      "options": [
        {
          "id": "A",
          "text": "Any prime number"
        },
        {
          "id": "B",
          "text": "An odd prime"
        },
        {
          "id": "C",
          "text": "Only 2"
        },
        {
          "id": "D",
          "text": "Only 3"
        }
      ],
      "question_number": 12,
      "question_text": "If p is a prime number and GCD $(p^2-1, p^2+1) = 2$, then the value of p must be:",
      "exam_type": "RRB",
      "sub_type": "RRB (NTPC)"
    },
    {
      "correct_answer": "D",
      "options": [
        {
          "id": "A",
          "text": "50 km/h"
        },
        {
          "id": "B",
          "text": "70 km/h"
        },
        {
          "id": "C",
          "text": "80 km/h"
        },
        {
          "id": "D",
          "text": "60 km/h"
        }
      ],
      "question_number": 13,
      "question_text": "A car covers a distance of 180 km in 3 hours. Find its average speed.",
      "exam_type": "RRB",
      "sub_type": "RRB (NTPC)"
    },
    {
      "correct_answer": "C",
      "options": [
        {
          "id": "A",
          "text": "710"
        },
        {
          "id": "B",
          "text": "690"
        },
        {
          "id": "C",
          "text": "720"
        },
        {
          "id": "D",
          "text": "700"
        }
      ],
      "question_number": 14,
      "question_text": "Riya and Neha have certain amount of money. If Riya gives ₹20 to Neha, then Riya will have three times as much money as Neha. However, if Neha gives ₹40 to Riya, then Riya will have five times as much money as Neha. What is the total amount of money (in ₹) that Riya and Neha initially had together?",
      "exam_type": "RRB",
      "sub_type": "RRB (NTPC)"
    },
    {
      "correct_answer": "D",
      "options": [
        {
          "id": "A",
          "text": "30 m"
        },
        {
          "id": "B",
          "text": "27 m"
        },
        {
          "id": "C",
          "text": "25 m"
        },
        {
          "id": "D",
          "text": "36 m"
        }
      ],
      "question_number": 15,
      "question_text": "In a fitness park, a straight walking path is divided into three consecutive segments. The length of the first and third segments are 18 m and 90 m respectively. If the length of the middle segment is the mean proportional between the other two, what is its length?",
      "exam_type": "RRB",
      "sub_type": "RRB (NTPC)"
    },
    {
      "correct_answer": "D",
      "options": [
        {
          "id": "A",
          "text": "1:4"
        },
        {
          "id": "B",
          "text": "2:1"
        },
        {
          "id": "C",
          "text": "1:3"
        },
        {
          "id": "D",
          "text": "1:2"
        }
      ],
      "question_number": 16,
      "question_text": "A solid right circular cylinder has curved surface area $1408\\pi$ $cm^2$. If the volume of the cylinder is maximum, then the ratio of radius to height is",
      "exam_type": "RRB",
      "sub_type": "RRB (NTPC)"
    },
    {
      "correct_answer": "D",
      "options": [
        {
          "id": "A",
          "text": "$60^\\circ$"
        },
        {
          "id": "B",
          "text": "$80^\\circ$"
        },
        {
          "id": "C",
          "text": "$50^\\circ$"
        },
        {
          "id": "D",
          "text": "$70^\\circ$"
        }
      ],
      "question_number": 17,
      "question_text": "In a parallelogram, the difference of two adjacent angles is $40^\\circ$. Find the measure of the smaller angle.",
      "exam_type": "RRB",
      "sub_type": "RRB (NTPC)"
    },
    {
      "correct_answer": "B",
      "options": [
        {
          "id": "A",
          "text": "2"
        },
        {
          "id": "B",
          "text": "3"
        },
        {
          "id": "C",
          "text": "4"
        },
        {
          "id": "D",
          "text": "1"
        }
      ],
      "question_number": 18,
      "question_text": "Two taps can fill a cistern in 4 hours and 18 hours, respectively. A third tap can empty it in 6 hours. How long (in hours) will it take to fill one-fourth of the empty cistern if all the taps are opened together?",
      "exam_type": "RRB",
      "sub_type": "RRB (NTPC)"
    },
    {
      "correct_answer": "B",
      "options": [
        {
          "id": "A",
          "text": "₹3,000"
        },
        {
          "id": "B",
          "text": "₹3,200"
        },
        {
          "id": "C",
          "text": "₹2,400"
        },
        {
          "id": "D",
          "text": "₹3,600"
        }
      ],
      "question_number": 19,
      "question_text": "The price of an article increases and decreases alternately by 20% every year. If the difference between the price at the end of the second year and third year is ₹1,920, find 40% of the price (in ₹) of the article at the end of the first year.",
      "exam_type": "RRB",
      "sub_type": "RRB (NTPC)"
    },
    {
      "correct_answer": "C",
      "options": [
        {
          "id": "A",
          "text": "B"
        },
        {
          "id": "B",
          "text": "C"
        },
        {
          "id": "C",
          "text": "A"
        },
        {
          "id": "D",
          "text": "D"
        }
      ],
      "question_number": 20,
      "question_text": "A shopkeeper offers the following schemes on toys of the same marked price.\n(A) Successive discounts of 20% and 30% on any number of toys bought.\n(B) Successive discounts of 20%, 4% and 4% on any number of toys bought.\n(C) 25% discount on the first 8 toys and 31% discount on each toy thereon.\n(D) 7 toys free of cost on buying 8 toys.\nA customer wants to buy 8 toys. Which of the above schemes is the least beneficial to him?",
      "exam_type": "RRB",
      "sub_type": "RRB (NTPC)"
    },
    {
      "correct_answer": "A",
      "options": [
        {
          "id": "A",
          "text": "17"
        },
        {
          "id": "B",
          "text": "15"
        },
        {
          "id": "C",
          "text": "21"
        },
        {
          "id": "D",
          "text": "19"
        }
      ],
      "question_number": 21,
      "question_text": "Simplify: $18 - [6 \\times 2 - (3 + 1)] \\div 7$",
      "exam_type": "RRB",
      "sub_type": "RRB (NTPC)"
    },
    {
      "correct_answer": "A",
      "options": [
        {
          "id": "A",
          "text": "2.16% increase"
        },
        {
          "id": "B",
          "text": "2.16% decrease"
        },
        {
          "id": "C",
          "text": "1.08% increase"
        },
        {
          "id": "D",
          "text": "1.08% decrease"
        }
      ],
      "question_number": 22,
      "question_text": "The price of an article is decreased by 24%, but the daily sale of the article is increased by 33%. Find the net effect on the daily sale receipts.",
      "exam_type": "RRB",
      "sub_type": "RRB (NTPC)"
    },
    {
      "correct_answer": "B",
      "options": [
        {
          "id": "A",
          "text": "₹270"
        },
        {
          "id": "B",
          "text": "₹300"
        },
        {
          "id": "C",
          "text": "₹280"
        },
        {
          "id": "D",
          "text": "₹320"
        }
      ],
      "question_number": 23,
      "question_text": "If 9 notebooks cost ₹135, how much will 20 notebooks of the same type cost?",
      "exam_type": "RRB",
      "sub_type": "RRB (NTPC)"
    },
    {
      "correct_answer": "B",
      "options": [
        {
          "id": "A",
          "text": "11"
        },
        {
          "id": "B",
          "text": "12"
        },
        {
          "id": "C",
          "text": "53"
        },
        {
          "id": "D",
          "text": "32"
        }
      ],
      "question_number": 24,
      "question_text": "Three numbers are in the ratio 5 : 14 : 9, and their LCM is 7560. Their HCF is:",
      "exam_type": "RRB",
      "sub_type": "RRB (NTPC)"
    },
    {
      "correct_answer": "C",
      "options": [
        {
          "id": "A",
          "text": "864"
        },
        {
          "id": "B",
          "text": "856"
        },
        {
          "id": "C",
          "text": "825"
        },
        {
          "id": "D",
          "text": "870"
        }
      ],
      "question_number": 25,
      "question_text": "A trader sells rice, claiming 1 kg but actually gives x grams. He marks the price 20% above the cost price and gives a 10% discount on the marked price. If his overall profit is 8%, find x.",
      "exam_type": "RRB",
      "sub_type": "RRB (NTPC)"
    },
    {
      "correct_answer": "D",
      "options": [
        {
          "id": "A",
          "text": "11"
        },
        {
          "id": "B",
          "text": "4"
        },
        {
          "id": "C",
          "text": "5"
        },
        {
          "id": "D",
          "text": "-3"
        }
      ],
      "question_number": 26,
      "question_text": "Find the value of m which satisfies\n$\\left(\\frac{23}{5}\\right)^{13} \\times \\left(\\frac{5}{23}\\right)^9 \\times \\left(\\frac{23}{5}\\right)^5 = \\left(\\frac{5}{23}\\right)^{6m + 9}$",
      "exam_type": "RRB",
      "sub_type": "RRB (NTPC)"
    },
    {
      "correct_answer": "C",
      "options": [
        {
          "id": "A",
          "text": "1,100"
        },
        {
          "id": "B",
          "text": "1,050"
        },
        {
          "id": "C",
          "text": "1,200"
        },
        {
          "id": "D",
          "text": "1,000"
        }
      ],
      "question_number": 27,
      "question_text": "A shopkeeper sells a watch for ₹840 after giving a 30% discount. What was the marked price (in ₹) of the watch?",
      "exam_type": "RRB",
      "sub_type": "RRB (NTPC)"
    },
    {
      "correct_answer": "D",
      "options": [
        {
          "id": "A",
          "text": "21 years"
        },
        {
          "id": "B",
          "text": "23 years"
        },
        {
          "id": "C",
          "text": "22 years"
        },
        {
          "id": "D",
          "text": "20 years"
        }
      ],
      "question_number": 28,
      "question_text": "Five years ago, the age of Kavita was one-third of the present age of her mother. After 5 years, the sum of their ages will be 75 years. What is Kavita's present age?",
      "exam_type": "RRB",
      "sub_type": "RRB (NTPC)"
    },
    {
      "correct_answer": "B",
      "options": [
        {
          "id": "A",
          "text": "180"
        },
        {
          "id": "B",
          "text": "170"
        },
        {
          "id": "C",
          "text": "185"
        },
        {
          "id": "D",
          "text": "165"
        }
      ],
      "question_number": 29,
      "question_text": "Sarang invested a certain sum of money at 10% per annum. After 2 years, he received ₹178.5 as compound interest, compounded annually. Find the corresponding simple interest (in ₹) for 2 years at the same rate.",
      "exam_type": "RRB",
      "sub_type": "RRB (NTPC)"
    },
    {
      "correct_answer": "B",
      "options": [
        {
          "id": "A",
          "text": "21"
        },
        {
          "id": "B",
          "text": "19"
        },
        {
          "id": "C",
          "text": "37"
        },
        {
          "id": "D",
          "text": "24"
        }
      ],
      "question_number": 30,
      "question_text": "The sum of two positive numbers is 77 and their product is 1392. The positive difference between them is:",
      "exam_type": "RRB",
      "sub_type": "RRB (NTPC)"
    },
    {
      "correct_answer": "C",
      "options": [
        {
          "id": "A",
          "text": "System output register"
        },
        {
          "id": "B",
          "text": "System secondary memory"
        },
        {
          "id": "C",
          "text": "System program counter"
        },
        {
          "id": "D",
          "text": "System input buffer unit"
        }
      ],
      "question_number": 31,
      "question_text": "The CPU retrieves the upcoming instruction for execution from which system component?",
      "exam_type": "RRB",
      "sub_type": "RRB (NTPC)"
    },
    {
      "correct_answer": "A",
      "options": [
        {
          "id": "A",
          "text": "Debendra Nath Tagore"
        },
        {
          "id": "B",
          "text": "Swami Vivekananda"
        },
        {
          "id": "C",
          "text": "Keshub Chandra Sen"
        },
        {
          "id": "D",
          "text": "Dwarkanath Tagore"
        }
      ],
      "question_number": 32,
      "question_text": "Who among the following succeeded Raja Ram Mohan Roy as the leader of the Brahmo Samaj?",
      "exam_type": "RRB",
      "sub_type": "RRB (NTPC)"
    },
    {
      "correct_answer": "A",
      "options": [
        {
          "id": "A",
          "text": "Chhattisgarh"
        },
        {
          "id": "B",
          "text": "Jharkhand"
        },
        {
          "id": "C",
          "text": "Madhya Pradesh"
        },
        {
          "id": "D",
          "text": "Odisha"
        }
      ],
      "question_number": 33,
      "question_text": "The sports event Bastar Olympics 2025 was launched in October 2023 in which Indian State?",
      "exam_type": "RRB",
      "sub_type": "RRB (NTPC)"
    },
    {
      "correct_answer": "D",
      "options": [
        {
          "id": "A",
          "text": "It remains the same, as the speed is constant in a given medium"
        },
        {
          "id": "B",
          "text": "It decreases rapidly because the air molecules move extremely slower"
        },
        {
          "id": "C",
          "text": "It decreases, because the air becomes less dense"
        },
        {
          "id": "D",
          "text": "It increases, because the air molecules move faster"
        }
      ],
      "question_number": 34,
      "question_text": "What happens to the speed of sound as the temperature of the air increases?",
      "exam_type": "RRB",
      "sub_type": "RRB (NTPC)"
    },
    {
      "correct_answer": "D",
      "options": [
        {
          "id": "A",
          "text": "Assam"
        },
        {
          "id": "B",
          "text": "Manipur"
        },
        {
          "id": "C",
          "text": "Meghalaya"
        },
        {
          "id": "D",
          "text": "Nagaland"
        }
      ],
      "question_number": 35,
      "question_text": "The Hornbill Festival, celebrated to showcase tribal culture, music, dance, and sports, is associated with which Indian state?",
      "exam_type": "RRB",
      "sub_type": "RRB (NTPC)"
    },
    {
      "correct_answer": "D",
      "options": [
        {
          "id": "A",
          "text": "Jhelam river"
        },
        {
          "id": "B",
          "text": "Beas river"
        },
        {
          "id": "C",
          "text": "Chenab river"
        },
        {
          "id": "D",
          "text": "Ravi river"
        }
      ],
      "question_number": 36,
      "question_text": "Which river rises west of the Rohtang pass in the Kullu hills of Himachal Pradesh and flows through the Chamba valley of the state?",
      "exam_type": "RRB",
      "sub_type": "RRB (NTPC)"
    },
    {
      "correct_answer": "B",
      "options": [
        {
          "id": "A",
          "text": "European Nations Trophy"
        },
        {
          "id": "B",
          "text": "Calcutta Cup"
        },
        {
          "id": "C",
          "text": "Millennium Cup"
        },
        {
          "id": "D",
          "text": "Triple Crown Trophy"
        }
      ],
      "question_number": 37,
      "question_text": "Which trophy is contested between the England and Scotland teams in the Rugby Six Nations Championship 2023?",
      "exam_type": "RRB",
      "sub_type": "RRB (NTPC)"
    },
    {
      "correct_answer": "D",
      "options": [
        {
          "id": "A",
          "text": "(g)"
        },
        {
          "id": "B",
          "text": "(aq)"
        },
        {
          "id": "C",
          "text": "(l)"
        },
        {
          "id": "D",
          "text": "(s)"
        }
      ],
      "question_number": 38,
      "question_text": "In the reaction $Na_2SO_4(aq) + BaCl_2(aq) \\to BaSO_4(s) + 2NaCl(aq)$, what will be the actual physical state that can replace (?)?",
      "exam_type": "RRB",
      "sub_type": "RRB (NTPC)"
    },
    {
      "correct_answer": "C",
      "options": [
        {
          "id": "A",
          "text": "Haruki Murakami"
        },
        {
          "id": "B",
          "text": "Gerald Murnane"
        },
        {
          "id": "C",
          "text": "Han Kang"
        },
        {
          "id": "D",
          "text": "Can Xue"
        }
      ],
      "question_number": 39,
      "question_text": "Who among the following won the 2024 Nobel Prize in literature?",
      "exam_type": "RRB",
      "sub_type": "RRB (NTPC)"
    },
    {
      "correct_answer": "B",
      "options": [
        {
          "id": "A",
          "text": "AI governance evaluation across countries"
        },
        {
          "id": "B",
          "text": "Digital infrastructure readiness"
        },
        {
          "id": "C",
          "text": "Global economic competitiveness"
        },
        {
          "id": "D",
          "text": "Environmental policy performance"
        }
      ],
      "question_number": 40,
      "question_text": "In 202S, the AGILE Index was introduced to measure which of the following areas globally?",
      "exam_type": "RRB",
      "sub_type": "RRB (NTPC)"
    },
    {
      "correct_answer": "D",
      "options": [
        {
          "id": "A",
          "text": "Quaternary"
        },
        {
          "id": "B",
          "text": "Primary"
        },
        {
          "id": "C",
          "text": "Secondary"
        },
        {
          "id": "D",
          "text": "Tertiary"
        }
      ],
      "question_number": 41,
      "question_text": "Service and trade fall under which type of economic activities?",
      "exam_type": "RRB",
      "sub_type": "RRB (NTPC)"
    },
    {
      "correct_answer": "C",
      "options": [
        {
          "id": "A",
          "text": "Manish Sisodia"
        },
        {
          "id": "B",
          "text": "Keshav Gupta"
        },
        {
          "id": "C",
          "text": "Parvesh Verma"
        },
        {
          "id": "D",
          "text": "Atishi Marlena"
        }
      ],
      "question_number": 42,
      "question_text": "Who became the Chief Minister of Delhi in February 202S, marking the Bharatiya Janata Party's return to power in the capital after 27 years?",
      "exam_type": "RRB",
      "sub_type": "RRB (NTPC)"
    },
    {
      "correct_answer": "B",
      "options": [
        {
          "id": "A",
          "text": "Rayleigh waves"
        },
        {
          "id": "B",
          "text": "P waves"
        },
        {
          "id": "C",
          "text": "S waves"
        },
        {
          "id": "D",
          "text": "Surface waves"
        }
      ],
      "question_number": 43,
      "question_text": "Which seismic waves are the fastest and travel through both solids and liquids inside the Earth?",
      "exam_type": "RRB",
      "sub_type": "RRB (NTPC)"
    },
    {
      "correct_answer": "B",
      "options": [
        {
          "id": "A",
          "text": "By supporting colonial factories and restricting local enterprises."
        },
        {
          "id": "B",
          "text": "By promoting indigenous industries and rejecting foreign products."
        },
        {
          "id": "C",
          "text": "By creating diplomatic councils to negotiate tariff concessions."
        },
        {
          "id": "D",
          "text": "By adopting military drills to train youth for organised defence."
        }
      ],
      "question_number": 44,
      "question_text": "How did the Swadeshi movement aim to counter British policies after 1905?",
      "exam_type": "RRB",
      "sub_type": "RRB (NTPC)"
    },
    {
      "correct_answer": "B",
      "options": [
        {
          "id": "A",
          "text": "10th Schedule"
        },
        {
          "id": "B",
          "text": "11th Schedule"
        },
        {
          "id": "C",
          "text": "9th Schedule"
        },
        {
          "id": "D",
          "text": "9th Schedule"
        }
      ],
      "question_number": 45,
      "question_text": "Which schedule contains the assigned functions of the Rural Local Self Government or the Panchayati Raj?",
      "exam_type": "RRB",
      "sub_type": "RRB (NTPC)"
    },
    {
      "correct_answer": "A",
      "options": [
        {
          "id": "A",
          "text": "2000"
        },
        {
          "id": "B",
          "text": "1997"
        },
        {
          "id": "C",
          "text": "2002"
        },
        {
          "id": "D",
          "text": "1999"
        }
      ],
      "question_number": 46,
      "question_text": "The Foreign Exchange Management Act (FEMA) was enacted in 1999 to replace the earlier FERA law. In which year did FEMA officially come into force?",
      "exam_type": "RRB",
      "sub_type": "RRB (NTPC)"
    },
    {
      "correct_answer": "C",
      "options": [
        {
          "id": "A",
          "text": "Civil Court"
        },
        {
          "id": "B",
          "text": "Consumer Court"
        },
        {
          "id": "C",
          "text": "Sessions Court"
        },
        {
          "id": "D",
          "text": "Family Court"
        }
      ],
      "question_number": 47,
      "question_text": "Which of the following courts is empowered to impose the highest punishment among the subordinate courts in India?",
      "exam_type": "RRB",
      "sub_type": "RRB (NTPC)"
    },
    {
      "correct_answer": "A",
      "options": [
        {
          "id": "A",
          "text": "It mainly builds or elevates parts of the crust"
        },
        {
          "id": "B",
          "text": "It only lowers existing landforms"
        },
        {
          "id": "C",
          "text": "It is controlled by rainfall and temperature"
        },
        {
          "id": "D",
          "text": "It requires running water to operate"
        }
      ],
      "question_number": 48,
      "question_text": "Which of the following statements about volcanism is most accurate in the context of geomorphic processes?",
      "exam_type": "RRB",
      "sub_type": "RRB (NTPC)"
    },
    {
      "correct_answer": "C",
      "options": [
        {
          "id": "A",
          "text": "Rudrasena II"
        },
        {
          "id": "B",
          "text": "Shashanka"
        },
        {
          "id": "C",
          "text": "Grahavarman"
        },
        {
          "id": "D",
          "text": "Devgupta"
        }
      ],
      "question_number": 49,
      "question_text": "Harshavardhana's sister, Rajyashri, was married to whom among the following?",
      "exam_type": "RRB",
      "sub_type": "RRB (NTPC)"
    },
    {
      "correct_answer": "A",
      "options": [
        {
          "id": "A",
          "text": "One: only Indian citizenship"
        },
        {
          "id": "B",
          "text": "Two: national and state"
        },
        {
          "id": "C",
          "text": "Two: national and regional"
        },
        {
          "id": "D",
          "text": "Three: local, state, national"
        }
      ],
      "question_number": 50,
      "question_text": "India follows which model of citizenship under its Constitution?",
      "exam_type": "RRB",
      "sub_type": "RRB (NTPC)"
    },
    {
      "correct_answer": "C",
      "options": [
        {
          "id": "A",
          "text": "Dyarchy in provinces"
        },
        {
          "id": "B",
          "text": "Separate electorates for Hindus only"
        },
        {
          "id": "C",
          "text": "Provincial autonomy and federal structure"
        },
        {
          "id": "D",
          "text": "Separate electorates for all communities"
        }
      ],
      "question_number": 51,
      "question_text": "The Government of India Act, 1935, provided __________.",
      "exam_type": "RRB",
      "sub_type": "RRB (NTPC)"
    },
    {
      "correct_answer": "C",
      "options": [
        {
          "id": "A",
          "text": "improving healthcare facilities"
        },
        {
          "id": "B",
          "text": "promoting agricultural exports"
        },
        {
          "id": "C",
          "text": "boosting manufacturing and job creation"
        },
        {
          "id": "D",
          "text": "enhancing tourism"
        }
      ],
      "question_number": 52,
      "question_text": "The 'Make in India' initiative launched by the Government of India in 2014 is primarily focused on which of the following?",
      "exam_type": "RRB",
      "sub_type": "RRB (NTPC)"
    },
    {
      "correct_answer": "C",
      "options": [
        {
          "id": "A",
          "text": "Mahendravarman"
        },
        {
          "id": "B",
          "text": "Pulakesin"
        },
        {
          "id": "C",
          "text": "Mayurasarman"
        },
        {
          "id": "D",
          "text": "Vidyasagar"
        }
      ],
      "question_number": 53,
      "question_text": "The Kadamba dynasty was founded by __________, an expert in guerrilla warfare.",
      "exam_type": "RRB",
      "sub_type": "RRB (NTPC)"
    },
    {
      "correct_answer": "C",
      "options": [
        {
          "id": "A",
          "text": "They can be enforced by any citizen through writ petitions."
        },
        {
          "id": "B",
          "text": "They are enforceable by the courts as Fundamental Rights."
        },
        {
          "id": "C",
          "text": "They are non-justiciable guidelines that aim to establish a just society."
        },
        {
          "id": "D",
          "text": "They are absolute and cannot be amended under any circumstance."
        }
      ],
      "question_number": 54,
      "question_text": "Which of the following statements about the Directive Principles of State Policy is correct?",
      "exam_type": "RRB",
      "sub_type": "RRB (NTPC)"
    },
    {
      "correct_answer": "C",
      "options": [
        {
          "id": "A",
          "text": "France"
        },
        {
          "id": "B",
          "text": "America"
        },
        {
          "id": "C",
          "text": "Russia"
        },
        {
          "id": "D",
          "text": "Japan"
        }
      ],
      "question_number": 55,
      "question_text": "In December 202S, which country officially extended an offer to India for the localised production of the fifth-generation Su-57 stealth fighter jets?",
      "exam_type": "RRB",
      "sub_type": "RRB (NTPC)"
    },
    {
      "correct_answer": "C",
      "options": [
        {
          "id": "A",
          "text": "High birth rates and high death rates"
        },
        {
          "id": "B",
          "text": "Low birth rates and low death rates"
        },
        {
          "id": "C",
          "text": "High birth rates and declining death rates"
        },
        {
          "id": "D",
          "text": "Low birth rates and high death rates"
        }
      ],
      "question_number": 56,
      "question_text": "What is the primary reason for the rapid population growth in developing countries during the second stage of the Demographic Transition Model?",
      "exam_type": "RRB",
      "sub_type": "RRB (NTPC)"
    },
    {
      "correct_answer": "B",
      "options": [
        {
          "id": "A",
          "text": "Shut Down, because it is the only way to achieve zero power consumption."
        },
        {
          "id": "B",
          "text": "Hibernate, because it saves the entire system state to the hard disk and powers down completely."
        },
        {
          "id": "C",
          "text": "Hybrid Sleep, because it uses both RAM and the hard drive to store the session."
        },
        {
          "id": "D",
          "text": "Sleep (Standby), because it maintains the session in RAM for a very quick resume."
        }
      ],
      "question_number": 57,
      "question_text": "A user is leaving their laptop unattended for the entire weekend and wants to ensure zero battery consumption while still being able to resume their exact work session (all open applications and tabs) quickly when they return on Monday. Which power-saving mode in Windows should they choose?",
      "exam_type": "RRB",
      "sub_type": "RRB (NTPC)"
    },
    {
      "correct_answer": "C",
      "options": [
        {
          "id": "A",
          "text": "N-M"
        },
        {
          "id": "B",
          "text": "$m/N^2$"
        },
        {
          "id": "C",
          "text": "$N/m^2$"
        },
        {
          "id": "D",
          "text": "N/m"
        }
      ],
      "question_number": 58,
      "question_text": "Pressure is measured in which SI unit?",
      "exam_type": "RRB",
      "sub_type": "RRB (NTPC)"
    },
    {
      "correct_answer": "B",
      "options": [
        {
          "id": "A",
          "text": "10-tonne Vertical Planetary Mixer"
        },
        {
          "id": "B",
          "text": "Automated liquid oxygen plant"
        },
        {
          "id": "C",
          "text": "3D-printed fuel injector assembly"
        },
        {
          "id": "D",
          "text": "Horizontal mixing facility"
        }
      ],
      "question_number": 59,
      "question_text": "Which first-of-its-kind propellant-production device did ISRO unveil in February 202S?",
      "exam_type": "RRB",
      "sub_type": "RRB (NTPC)"
    },
    {
      "correct_answer": "A",
      "options": [
        {
          "id": "A",
          "text": "The President of India"
        },
        {
          "id": "B",
          "text": "The Chief Minister of the nearest state"
        },
        {
          "id": "C",
          "text": "The Parliament of India"
        },
        {
          "id": "D",
          "text": "The Prime Minister of India"
        }
      ],
      "question_number": 60,
      "question_text": "If a new union territory is created, who will appoint its administrator?",
      "exam_type": "RRB",
      "sub_type": "RRB (NTPC)"
    },
    {
      "correct_answer": "A",
      "options": [
        {
          "id": "A",
          "text": "Low resistivity"
        },
        {
          "id": "B",
          "text": "Constant resistivity"
        },
        {
          "id": "C",
          "text": "No resistivity"
        },
        {
          "id": "D",
          "text": "High resistivity"
        }
      ],
      "question_number": 61,
      "question_text": "Electrical conductors are materials that possess which of the following properties?",
      "exam_type": "RRB",
      "sub_type": "RRB (NTPC)"
    },
    {
      "correct_answer": "B",
      "options": [
        {
          "id": "A",
          "text": "Ctrl + Tab"
        },
        {
          "id": "B",
          "text": "Ctrl + S"
        },
        {
          "id": "C",
          "text": "Ctrl + F"
        },
        {
          "id": "D",
          "text": "Ctrl + V"
        }
      ],
      "question_number": 62,
      "question_text": "Which shortcut saves the current file in Microsoft Word or Microsoft Excel?",
      "exam_type": "RRB",
      "sub_type": "RRB (NTPC)"
    },
    {
      "correct_answer": "A",
      "options": [
        {
          "id": "A",
          "text": "Sun Temple"
        },
        {
          "id": "B",
          "text": "Lingaraja Temple"
        },
        {
          "id": "C",
          "text": "Jagannath Temple"
        },
        {
          "id": "D",
          "text": "Mukteshwara Temple"
        }
      ],
      "question_number": 63,
      "question_text": "Which temple in Odisha is renowned for its chariot-shaped structure and is a prime example of Kalinga architecture?",
      "exam_type": "RRB",
      "sub_type": "RRB (NTPC)"
    },
    {
      "correct_answer": "C",
      "options": [
        {
          "id": "A",
          "text": "Manipuri"
        },
        {
          "id": "B",
          "text": "Bharatanatyam"
        },
        {
          "id": "C",
          "text": "Odissi"
        },
        {
          "id": "D",
          "text": "Kathakali"
        }
      ],
      "question_number": 64,
      "question_text": "Aruna Mohanty, who received the Padma Shree award in 2017, is associated with which of the following dance forms?",
      "exam_type": "RRB",
      "sub_type": "RRB (NTPC)"
    },
    {
      "correct_answer": "A",
      "options": [
        {
          "id": "A",
          "text": "China"
        },
        {
          "id": "B",
          "text": "United States"
        },
        {
          "id": "C",
          "text": "Brazil"
        },
        {
          "id": "D",
          "text": "Canada"
        }
      ],
      "question_number": 65,
      "question_text": "As per International Renewable Energy Agency (IRENA) data, which country has the largest installed hydropower capacity in the world as of 202S?",
      "exam_type": "RRB",
      "sub_type": "RRB (NTPC)"
    },
    {
      "correct_answer": "B",
      "options": [
        {
          "id": "A",
          "text": "Administrative relations"
        },
        {
          "id": "B",
          "text": "Legislative relations"
        },
        {
          "id": "C",
          "text": "Judicial relations"
        },
        {
          "id": "D",
          "text": "Financial relations"
        }
      ],
      "question_number": 66,
      "question_text": "Articles 245 to 255 of Part XI of the Indian Constitution primarily deal with which aspect of Centre-State relations?",
      "exam_type": "RRB",
      "sub_type": "RRB (NTPC)"
    },
    {
      "correct_answer": "A",
      "options": [
        {
          "id": "A",
          "text": "Lucknow"
        },
        {
          "id": "B",
          "text": "Mumbai"
        },
        {
          "id": "C",
          "text": "Hyderabad"
        },
        {
          "id": "D",
          "text": "New Delhi"
        }
      ],
      "question_number": 67,
      "question_text": "In November 202S, which city hosted the Syed Modi India International Badminton Tournament?",
      "exam_type": "RRB",
      "sub_type": "RRB (NTPC)"
    },
    {
      "correct_answer": "B",
      "options": [
        {
          "id": "A",
          "text": "Instruction Set"
        },
        {
          "id": "B",
          "text": "Cache Memory"
        },
        {
          "id": "C",
          "text": "Address Decoder"
        },
        {
          "id": "D",
          "text": "CPU Fan"
        }
      ],
      "question_number": 68,
      "question_text": "A student notices that arithmetic results appear instantly, but loading data from main memory is slower. Which CPU feature primarily reduces this delay by keeping frequently used data closer to the processor?",
      "exam_type": "RRB",
      "sub_type": "RRB (NTPC)"
    },
    {
      "correct_answer": "D",
      "options": [
        {
          "id": "A",
          "text": "McLaren"
        },
        {
          "id": "B",
          "text": "Ferrari"
        },
        {
          "id": "C",
          "text": "Racing Bulls"
        },
        {
          "id": "D",
          "text": "Red Bull Racing"
        }
      ],
      "question_number": 69,
      "question_text": "In October 202S, Max Verstappen won the United States Grand Prix representing which of the following teams?",
      "exam_type": "RRB",
      "sub_type": "RRB (NTPC)"
    },
    {
      "correct_answer": "B",
      "options": [
        {
          "id": "A",
          "text": "Reducing foreign trade"
        },
        {
          "id": "B",
          "text": "Economic growth and stability"
        },
        {
          "id": "C",
          "text": "Increasing fiscal deficit"
        },
        {
          "id": "D",
          "text": "Increasing inflation"
        }
      ],
      "question_number": 70,
      "question_text": "What is the main objective of India's fiscal policy?",
      "exam_type": "RRB",
      "sub_type": "RRB (NTPC)"
    },
    {
      "correct_answer": "B",
      "options": [
        {
          "id": "A",
          "text": "7"
        },
        {
          "id": "B",
          "text": "8"
        },
        {
          "id": "C",
          "text": "7"
        },
        {
          "id": "D",
          "text": "2"
        }
      ],
      "question_number": 71,
      "question_text": "In a certain code language, 'DOLE' is coded as '7348' and 'LEMO' is coded as '2738'. What is the code for 'M' in the given code language?",
      "exam_type": "RRB",
      "sub_type": "RRB (NTPC)"
    },
    {
      "correct_answer": "A",
      "options": [
        {
          "id": "A",
          "text": "Two"
        },
        {
          "id": "B",
          "text": "One"
        },
        {
          "id": "C",
          "text": "Four"
        },
        {
          "id": "D",
          "text": "Three"
        }
      ],
      "question_number": 72,
      "question_text": "In the English alphabetical word WORTHLESSLY is changed to the second letter following it in the English alphabetical order AND each consonant is changed to the letter immediately preceding it in the English alphabetical order. How many letters will appear exactly twice in the group of letters thus formed?",
      "exam_type": "RRB",
      "sub_type": "RRB (NTPC)"
    },
    {
      "correct_answer": "C",
      "options": [
        {
          "id": "A",
          "text": "M"
        },
        {
          "id": "B",
          "text": "Q"
        },
        {
          "id": "C",
          "text": "C"
        },
        {
          "id": "D",
          "text": "F"
        }
      ],
      "question_number": 73,
      "question_text": "Each vowel in the word READING is changed to the letter immediately following it in the English alphabetical order and each consonant is changed to the letter immediately preceding it in the English alphabetical order. Which of the following letters will appear exactly twice in the group of letters thus formed?",
      "exam_type": "RRB",
      "sub_type": "RRB (NTPC)"
    },
    {
      "correct_answer": "B",
      "options": [
        {
          "id": "A",
          "text": "Immediate left"
        },
        {
          "id": "B",
          "text": "Second to the left"
        },
        {
          "id": "C",
          "text": "Second to the right"
        },
        {
          "id": "D",
          "text": "Immediate right"
        }
      ],
      "question_number": 74,
      "question_text": "Six people A, B, P, Q, C and D are sitting in a straight line. They all are facing towards North. C is sitting to the immediate left of P. Q is a little to the right of the left of B. A sits second to the right of P. What is the position of C with respect to D?",
      "exam_type": "RRB",
      "sub_type": "RRB (NTPC)"
    },
    {
      "correct_answer": "D",
      "options": [
        {
          "id": "A",
          "text": "One"
        },
        {
          "id": "B",
          "text": "Three"
        },
        {
          "id": "C",
          "text": "None"
        },
        {
          "id": "D",
          "text": "Two"
        }
      ],
      "question_number": 75,
      "question_text": "If 2 is added to each odd digit and 1 is subtracted from each even digit in the number 573849, how many digits will appear more than once in the new number thus formed?",
      "exam_type": "RRB",
      "sub_type": "RRB (NTPC)"
    },
    {
      "correct_answer": "D",
      "options": [
        {
          "id": "A",
          "text": "JEK 55"
        },
        {
          "id": "B",
          "text": "KDH 56"
        },
        {
          "id": "C",
          "text": "PIM 56"
        },
        {
          "id": "D",
          "text": "SBU 56"
        }
      ],
      "question_number": 76,
      "question_text": "Which of the following letter-number clusters will replace the question mark (?) in the given series to make it logically complete?\nSDH 12 NKR 23 URY 34 BYF 45 ?",
      "exam_type": "RRB",
      "sub_type": "RRB (NTPC)"
    },
    {
      "correct_answer": "B",
      "options": [
        {
          "id": "A",
          "text": "Only conclusion (I) follows"
        },
        {
          "id": "B",
          "text": "Only conclusion (II) follows"
        },
        {
          "id": "C",
          "text": "Neither conclusion (I) nor (II) follows"
        },
        {
          "id": "D",
          "text": "Both conclusions (I) and (II) follow"
        }
      ],
      "question_number": 77,
      "question_text": "Read the given statement(s) and conclusions carefully. Assuming that the information given in the statements is true, even if it appears to be at variance with commonly known facts, decide which of the given conclusions logically follow(s) from the statement(s).\nStatements:\nSome fans are cars.\nNo car is a bus.\nConclusions:\n(I) Some fans are buses.\n(II) Some cars are fans.",
      "exam_type": "RRB",
      "sub_type": "RRB (NTPC)"
    },
    {
      "correct_answer": "C",
      "options": [
        {
          "id": "A",
          "text": "UPSS4"
        },
        {
          "id": "B",
          "text": "UPTS3"
        },
        {
          "id": "C",
          "text": "UPTS4"
        },
        {
          "id": "D",
          "text": "UPTS4"
        }
      ],
      "question_number": 78,
      "question_text": "Which of the following letter-number clusters will replace the question mark (?) in the given series to make it logically complete?\nMHL21 OJN29 QLP37 SNR45 ?",
      "exam_type": "RRB",
      "sub_type": "RRB (NTPC)"
    },
    {
      "correct_answer": "B",
      "options": [
        {
          "id": "A",
          "text": "35"
        },
        {
          "id": "B",
          "text": "298"
        },
        {
          "id": "C",
          "text": "760"
        },
        {
          "id": "D",
          "text": "427"
        }
      ],
      "question_number": 79,
      "question_text": "If '+' means '$\\times$', '-' means '$\\div$', '$\\times$' means '-', '$\\div$' means '+', then what will come in place of the question mark (?) in the following equation?\n$32 \\times 23 - 14 + 463 \\div 232 = ?$",
      "exam_type": "RRB",
      "sub_type": "RRB (NTPC)"
    },
    {
      "correct_answer": "A",
      "options": [
        {
          "id": "A",
          "text": "South-west"
        },
        {
          "id": "B",
          "text": "South-east"
        },
        {
          "id": "C",
          "text": "North-west"
        },
        {
          "id": "D",
          "text": "North-east"
        }
      ],
      "question_number": 80,
      "question_text": "Town G is to the west of Town H. Town I is to the north of Town G. Town J is to the east of Town I. Town K is to the south-east of Town H. Town H is to the north-east of Town K. What is the position of Town G with respect to Town J?",
      "exam_type": "RRB",
      "sub_type": "RRB (NTPC)"
    },
    {
      "correct_answer": "C",
      "options": [
        {
          "id": "A",
          "text": "Mother"
        },
        {
          "id": "B",
          "text": "Son"
        },
        {
          "id": "C",
          "text": "Brother"
        },
        {
          "id": "D",
          "text": "Husband"
        }
      ],
      "question_number": 81,
      "question_text": "In a certain code language,\n'A' means 'A is the son of B',\n'A = B' means 'A is the brother of B',\n'A * B' means 'A is the sister of B' and\n'A ~ B' means 'A is the father of B'.\nHow is S related to Z if 'S = W * R + T ~ Z'?",
      "exam_type": "RRB",
      "sub_type": "RRB (NTPC)"
    },
    {
      "correct_answer": "A",
      "options": [
        {
          "id": "A",
          "text": "OL-JQ"
        },
        {
          "id": "B",
          "text": "UR-RW"
        },
        {
          "id": "C",
          "text": "LU-SY"
        },
        {
          "id": "D",
          "text": "RO-MT"
        }
      ],
      "question_number": 82,
      "question_text": "Based on the English alphabetical order, three of the following four letter-cluster pairs are alike in a certain way and thus form a group. Which is the one that does not belong to that group? (Note: The odd one out is based on the number of consonants/vowels or their position in the letter cluster.)",
      "exam_type": "RRB",
      "sub_type": "RRB (NTPC)"
    },
    {
      "correct_answer": "B",
      "options": [
        {
          "id": "A",
          "text": "HOGS - OHGS - SOGH"
        },
        {
          "id": "B",
          "text": "TONG - ONTGT - OGNT"
        },
        {
          "id": "C",
          "text": "UGLY - GLLY - GLYU"
        },
        {
          "id": "D",
          "text": "MIND - MNID - DNIM"
        }
      ],
      "question_number": 83,
      "question_text": "In the following triad, each group of letters is related to the subsequent one following a certain logic. Select, from the given options, the one which follows the same logic.\nSIM - LJH, DIME - EDOM\nMODE - ODDM",
      "exam_type": "RRB",
      "sub_type": "RRB (NTPC)"
    },
    {
      "correct_answer": "D",
      "options": [
        {
          "id": "A",
          "text": "Three"
        },
        {
          "id": "B",
          "text": "One"
        },
        {
          "id": "C",
          "text": "None"
        },
        {
          "id": "D",
          "text": "Two"
        }
      ],
      "question_number": 84,
      "question_text": "Seven people H, I, J, P, Q, V and Z are sitting in a row facing north. Only J sits to the left of W. Only four people sit between J and K. Only P sits between V and J. K is not an immediate neighbor of Y. How many people sit to the right of Z?",
      "exam_type": "RRB",
      "sub_type": "RRB (NTPC)"
    },
    {
      "correct_answer": "B",
      "options": [
        {
          "id": "A",
          "text": "161"
        },
        {
          "id": "B",
          "text": "143"
        },
        {
          "id": "C",
          "text": "155"
        },
        {
          "id": "D",
          "text": "152"
        }
      ],
      "question_number": 85,
      "question_text": "What should come in place of '?' in the given series?\n38 55 74 95 118 ?",
      "exam_type": "RRB",
      "sub_type": "RRB (NTPC)"
    },
    {
      "correct_answer": "C",
      "options": [
        {
          "id": "A",
          "text": "UY 1"
        },
        {
          "id": "B",
          "text": "NJ 2"
        },
        {
          "id": "C",
          "text": "ON 2"
        },
        {
          "id": "D",
          "text": "TY 5"
        }
      ],
      "question_number": 86,
      "question_text": "WT 16 is related to XW -1 in a certain way. In the same way, DE 9 is related to EH -8. To which of the following is NK 19 related, following the same logic?",
      "exam_type": "RRB",
      "sub_type": "RRB (NTPC)"
    },
    {
      "correct_answer": "B",
      "options": [
        {
          "id": "A",
          "text": "107"
        },
        {
          "id": "B",
          "text": "106"
        },
        {
          "id": "C",
          "text": "105"
        },
        {
          "id": "D",
          "text": "108"
        }
      ],
      "question_number": 87,
      "question_text": "Tus ranked $50^{th}$ from the bottom and $51^{st}$ from the top in his class. How many students are there in his class?",
      "exam_type": "RRB",
      "sub_type": "RRB (NTPC)"
    },
    {
      "correct_answer": "C",
      "options": [
        {
          "id": "A",
          "text": "JT 4"
        },
        {
          "id": "B",
          "text": "JT 5"
        },
        {
          "id": "C",
          "text": "UG 3"
        },
        {
          "id": "D",
          "text": "RW 1"
        }
      ],
      "question_number": 88,
      "question_text": "QQ 5 is related to VR -6 in a certain way. In the same way, LV 12 is related to QW 1. To which of the following is ES 16 related, following the same logic?",
      "exam_type": "RRB",
      "sub_type": "RRB (NTPC)"
    },
    {
      "correct_answer": "A",
      "options": [
        {
          "id": "A",
          "text": "58"
        },
        {
          "id": "B",
          "text": "66"
        },
        {
          "id": "C",
          "text": "60"
        },
        {
          "id": "D",
          "text": "58"
        }
      ],
      "question_number": 89,
      "question_text": "In a certain code language, \"EUOA\" is coded as \"53\" and \"YFMP\" is coded as \"71\". What is the code for \"RIZB\" in that given language?",
      "exam_type": "RRB",
      "sub_type": "RRB (NTPC)"
    },
    {
      "correct_answer": "C",
      "options": [
        {
          "id": "A",
          "text": "FSM"
        },
        {
          "id": "B",
          "text": "ERL"
        },
        {
          "id": "C",
          "text": "DPN"
        },
        {
          "id": "D",
          "text": "GTC"
        }
      ],
      "question_number": 90,
      "question_text": "What should come in place of '?' in the given series based on the English alphabetical order?\nTGA WJD ZMG CPJ ?",
      "exam_type": "RRB",
      "sub_type": "RRB (NTPC)"
    },
    {
      "correct_answer": "B",
      "options": [
        {
          "id": "A",
          "text": "(132, 229, 98)"
        },
        {
          "id": "B",
          "text": "(113, 178, 65)"
        },
        {
          "id": "C",
          "text": "(135, 187, 62)"
        },
        {
          "id": "D",
          "text": "(201, 243, 43)"
        }
      ],
      "question_number": 91,
      "question_text": "Select the set in which the numbers are related in the same way as are the numbers of the following sets.\n(Note: Operations should be performed on the whole numbers, without breaking down the numbers into their constituent digits. E.g. 13 can be given as 13. Breaking 13 into 1 and 3 and then performing mathematical operations on 1 and 3 is not allowed.)\n(163, 186, 23)\n(101, 100, 96)",
      "exam_type": "RRB",
      "sub_type": "RRB (NTPC)"
    },
    {
      "correct_answer": "A",
      "options": [
        {
          "id": "A",
          "text": "RSC"
        },
        {
          "id": "B",
          "text": "BGC"
        },
        {
          "id": "C",
          "text": "LNI"
        },
        {
          "id": "D",
          "text": "NOK"
        }
      ],
      "question_number": 92,
      "question_text": "Based on the English alphabetical order, three of the following four are alike in a certain way and thus form a group. Which is the one that does not belong to that group?\n(Note: The odd man out is not based on the number of consonants/vowels or their position in the letter cluster.)",
      "exam_type": "RRB",
      "sub_type": "RRB (NTPC)"
    },
    {
      "correct_answer": "D",
      "options": [
        {
          "id": "A",
          "text": "Four"
        },
        {
          "id": "B",
          "text": "Two"
        },
        {
          "id": "C",
          "text": "One"
        },
        {
          "id": "D",
          "text": "Three"
        }
      ],
      "question_number": 93,
      "question_text": "Refer to the following letter series and answer the question that follows. Counting to be done from left to right only.\n(Left) U L Y M R D E L C D A E H R O H F X L D W H (Right)\nHow many such vowels are there, each of which is immediately preceded by a consonant and also immediately followed by a consonant?",
      "exam_type": "RRB",
      "sub_type": "RRB (NTPC)"
    },
    {
      "correct_answer": "D",
      "options": [
        {
          "id": "A",
          "text": "Three"
        },
        {
          "id": "B",
          "text": "One"
        },
        {
          "id": "C",
          "text": "Four"
        },
        {
          "id": "D",
          "text": "Five"
        }
      ],
      "question_number": 94,
      "question_text": "Seven boxes M, N, O, P, X, Y and Z are kept one over the other but not necessarily in the same order. Y is kept second from the bottom. Only three boxes are kept between Y and P. X is kept at the topmost position. Only three boxes are kept between O and P. M is kept at one of the positions above O. How many boxes are kept between X and M?",
      "exam_type": "RRB",
      "sub_type": "RRB (NTPC)"
    },
    {
      "correct_answer": "C",
      "options": [
        {
          "id": "A",
          "text": "TPR"
        },
        {
          "id": "B",
          "text": "NJK"
        },
        {
          "id": "C",
          "text": "PLN"
        },
        {
          "id": "D",
          "text": "VRT"
        }
      ],
      "question_number": 95,
      "question_text": "Based on the English alphabetical order, three of the following four letter-clusters are alike in a certain way and thus form a group. Which is the one that DOES NOT belong to that group?\n(Note: The odd one out is not based on the number of consonants/vowels or their position in the letter-cluster.)",
      "exam_type": "RRB",
      "sub_type": "RRB (NTPC)"
    },
    {
      "correct_answer": "B",
      "options": [
        {
          "id": "A",
          "text": "131"
        },
        {
          "id": "B",
          "text": "91"
        },
        {
          "id": "C",
          "text": "99"
        },
        {
          "id": "D",
          "text": "111"
        }
      ],
      "question_number": 96,
      "question_text": "What should come in place of '?' in the given series?\n90 95 126 190 315 ?",
      "exam_type": "RRB",
      "sub_type": "RRB (NTPC)"
    },
    {
      "correct_answer": "B",
      "options": [
        {
          "id": "A",
          "text": "Neither conclusion (I) nor (II) follows"
        },
        {
          "id": "B",
          "text": "Only conclusion (II) follows"
        },
        {
          "id": "C",
          "text": "Both conclusions (I) and (II) follow"
        },
        {
          "id": "D",
          "text": "Only conclusion (I) follows"
        }
      ],
      "question_number": 97,
      "question_text": "Read the given statements and conclusions carefully. Assume that the information given in the statements is true, even if it appears to be at variance with commonly known facts. You have to decide which of the given conclusions logically follow(s) from the statements.\nStatements:\nAll routers are dongles. All routers are phones\nConclusion (I) - All phones are routers\nConclusion (II) - Some dongles are phones",
      "exam_type": "RRB",
      "sub_type": "RRB (NTPC)"
    },
    {
      "correct_answer": "D",
      "options": [
        {
          "id": "A",
          "text": "Son's wife's sister"
        },
        {
          "id": "B",
          "text": "Son's wife"
        },
        {
          "id": "C",
          "text": "Wife's sister"
        },
        {
          "id": "D",
          "text": "Mother's sister"
        }
      ],
      "question_number": 98,
      "question_text": "In a certain code language,\nA + B means 'A is the wife of B',\nA - B means 'A is the daughter of B',\nA % B means 'A is the mother of B' and\nA $\\times$ B means 'A is the father of B'.\nBased on the above, how is C related to M if 'C $\\times$ D + E $\\times$ F + L $\\times$ M'?",
      "exam_type": "RRB",
      "sub_type": "RRB (NTPC)"
    },
    {
      "correct_answer": "C",
      "options": [
        {
          "id": "A",
          "text": "Three"
        },
        {
          "id": "B",
          "text": "One"
        },
        {
          "id": "C",
          "text": "Two"
        },
        {
          "id": "D",
          "text": "Four"
        }
      ],
      "question_number": 99,
      "question_text": "Seven boxes B, C, D, E, Q, R and S are kept one over the other but not necessarily in the same order. Only one box is kept above D. Only two boxes are kept between R and S. Only three boxes are kept between D and E. Only Q is kept below C. B is not kept immediately above S. How many boxes are kept between B and Q?",
      "exam_type": "RRB",
      "sub_type": "RRB (NTPC)"
    },
    {
      "correct_answer": "B",
      "options": [
        {
          "id": "A",
          "text": "Three"
        },
        {
          "id": "B",
          "text": "Two"
        },
        {
          "id": "C",
          "text": "One"
        },
        {
          "id": "D",
          "text": "Four"
        }
      ],
      "question_number": 100,
      "question_text": "If 2 is added to each even digit and 1 is subtracted from each odd digit in the number 4314578, then how many digits will appear more than once in the new number thus formed?",
      "exam_type": "RRB",
      "sub_type": "RRB (NTPC)"
    }
  ]
}