{
  "questions": [
    {
      "correct_answer": "B",
      "options": [
        {
          "id": "A",
          "text": "₹6,500"
        },
        {
          "id": "B",
          "text": "₹6,000"
        },
        {
          "id": "C",
          "text": "₹5,800"
        },
        {
          "id": "D",
          "text": "₹6,400"
        }
      ],
      "question_number": 1,
      "question_text": "An amount of ₹6,900 is obtained after 3 years at simple interest at the rate of 5% interest per annum. What is the principal invested?",
      "exam_type": "Banking",
      "sub_type": "SBI PO Prelims"
    },
    {
      "correct_answer": "D",
      "options": [
        {
          "id": "A",
          "text": "30"
        },
        {
          "id": "B",
          "text": "25"
        },
        {
          "id": "C",
          "text": "26"
        },
        {
          "id": "D",
          "text": "24"
        }
      ],
      "question_number": 2,
      "question_text": "The present ages of two persons, X and Y, are in the ratio 4 : 5. Five years from now, the difference between X's age and Y's age will be 3 years. Find the sum of their present ages (in years).",
      "exam_type": "Banking",
      "sub_type": "SBI PO Prelims"
    },
    {
      "correct_answer": "B",
      "options": [
        {
          "id": "A",
          "text": "10"
        },
        {
          "id": "B",
          "text": "5"
        },
        {
          "id": "C",
          "text": "15"
        },
        {
          "id": "D",
          "text": "20"
        }
      ],
      "question_number": 3,
      "question_text": "Article M is sold at a reduction of ₹3,000 from its original price, and Article N is sold at a reduction of ₹2,500 from its original price. If the original prices of both articles were ₹10,000, reduction in price of M is R1%, and reduction in price of N is R2%. Find the difference between R1 and R2.",
      "exam_type": "Banking",
      "sub_type": "SBI PO Prelims"
    },
    {
      "correct_answer": "D",
      "options": [
        {
          "id": "A",
          "text": "42.562 m"
        },
        {
          "id": "B",
          "text": "40.752 m"
        },
        {
          "id": "C",
          "text": "41.652 m"
        },
        {
          "id": "D",
          "text": "40.688 m"
        }
      ],
      "question_number": 4,
      "question_text": "A delivery drone is hovering at a fixed point in the air. From two points on the ground in a straight line on opposite sides of the drone, the angles of elevation of the drone are $30^\\circ$ and $60^\\circ$. If the horizontal distance between the two points is $10\\sqrt{3}$ m, find the vertical height at which the drone is hovering. (Take $\\sqrt{3} = 1.73$)",
      "exam_type": "Banking",
      "sub_type": "SBI PO Prelims"
    },
    {
      "correct_answer": "A",
      "options": [
        {
          "id": "A",
          "text": "$(a - b)$"
        },
        {
          "id": "B",
          "text": "$(a + b)$"
        },
        {
          "id": "C",
          "text": "$(a + b)^2$"
        },
        {
          "id": "D",
          "text": "$\\frac{(a - b)^2}{(a + b)}$"
        }
      ],
      "question_number": 5,
      "question_text": "Find the third proportional to $(a^2 - b^2)$ and $(a + b)$, given that $a \\neq b$.",
      "exam_type": "Banking",
      "sub_type": "SBI PO Prelims"
    },
    {
      "correct_answer": "D",
      "options": [
        {
          "id": "A",
          "text": "$\\frac{12}{11}$"
        },
        {
          "id": "B",
          "text": "$\\frac{3}{10}$"
        },
        {
          "id": "C",
          "text": "$\\frac{11}{1}$"
        },
        {
          "id": "D",
          "text": "$\\frac{2}{3}$"
        }
      ],
      "question_number": 6,
      "question_text": "Simplify: $$\\frac{\\frac{10}{18}}{\\frac{9}{9}} \\div \\left( \\frac{4}{9} \\times \\frac{18}{12} + \\frac{5}{6} \\right) + \\frac{9}{9} \\div \\frac{27}{15} \\text{ of } \\frac{15}{9}$$",
      "exam_type": "Banking",
      "sub_type": "SBI PO Prelims"
    },
    {
      "correct_answer": "B",
      "options": [
        {
          "id": "A",
          "text": "$10\\sqrt{2}$ and $24\\sqrt{2}$"
        },
        {
          "id": "B",
          "text": "10 and 24"
        },
        {
          "id": "C",
          "text": "$5\\sqrt{2}$ and $12\\sqrt{2}$"
        },
        {
          "id": "D",
          "text": "5 and 12"
        }
      ],
      "question_number": 7,
      "question_text": "The diagonals of a rhombus are in the ratio $5 : 12$ and its area is $240 \\text{ cm}^2$. Find the lengths (in cm) of the diagonals.",
      "exam_type": "Banking",
      "sub_type": "SBI PO Prelims"
    },
    {
      "correct_answer": "B",
      "options": [
        {
          "id": "A",
          "text": "2"
        },
        {
          "id": "B",
          "text": "2"
        },
        {
          "id": "C",
          "text": "3"
        },
        {
          "id": "D",
          "text": "4"
        }
      ],
      "question_number": 8,
      "question_text": "Three numbers are in the ratio $10 : 13 : 11$, and their LCM is 2860. Their HCF is:",
      "exam_type": "Banking",
      "sub_type": "SBI PO Prelims"
    },
    {
      "correct_answer": "D",
      "options": [
        {
          "id": "A",
          "text": "12 cm"
        },
        {
          "id": "B",
          "text": "10 cm"
        },
        {
          "id": "C",
          "text": "8 cm"
        },
        {
          "id": "D",
          "text": "9 cm"
        }
      ],
      "question_number": 9,
      "question_text": "The lengths of two rods are 4 cm and 6 cm. A third rod is made such that the three rods are in continued proportion. What will be the length of the third rod?",
      "exam_type": "Banking",
      "sub_type": "SBI PO Prelims"
    },
    {
      "correct_answer": "C",
      "options": [
        {
          "id": "A",
          "text": "7"
        },
        {
          "id": "B",
          "text": "$6\\sqrt{6}$"
        },
        {
          "id": "C",
          "text": "$6\\sqrt{3}$"
        },
        {
          "id": "D",
          "text": "$8\\sqrt{3}$"
        }
      ],
      "question_number": 10,
      "question_text": "A solid cylinder of radius 6 cm and height 14 cm is melted and recast into a hollow cylinder of half the height of the original cylinder. If the outer diameter of the hollow cylinder is twice its inner radius, find the outer radius (in cm) of the hollow cylinder.",
      "exam_type": "Banking",
      "sub_type": "SBI PO Prelims"
    },
    {
      "correct_answer": "D",
      "options": [
        {
          "id": "A",
          "text": "63"
        },
        {
          "id": "B",
          "text": "53"
        },
        {
          "id": "C",
          "text": "40"
        },
        {
          "id": "D",
          "text": "24"
        }
      ],
      "question_number": 11,
      "question_text": "The sides of a triangle are 51 cm, 35 cm, and 26 cm. What is the length (in cm) of its altitude corresponding to the side with a length of 35 cm?",
      "exam_type": "Banking",
      "sub_type": "SBI PO Prelims"
    },
    {
      "correct_answer": "B",
      "options": [
        {
          "id": "A",
          "text": "1"
        },
        {
          "id": "B",
          "text": "7"
        },
        {
          "id": "C",
          "text": "5"
        },
        {
          "id": "D",
          "text": "3"
        }
      ],
      "question_number": 12,
      "question_text": "What is the smallest number that must be added to 4583 so that the resulting number is divisible by 9?",
      "exam_type": "Banking",
      "sub_type": "SBI PO Prelims"
    },
    {
      "correct_answer": "C",
      "options": [
        {
          "id": "A",
          "text": "7.8"
        },
        {
          "id": "B",
          "text": "18.9"
        },
        {
          "id": "C",
          "text": "7.1"
        },
        {
          "id": "D",
          "text": "3.8"
        }
      ],
      "question_number": 13,
      "question_text": "Mike, Connor and Floyd can finish a certain piece of work in 8, 22 and 33 days respectively. All three of them started the work together. Mike left the work after 4 days and Connor left just 2 days before the work was completed. Find the total number of days taken for the work to be completed.",
      "exam_type": "Banking",
      "sub_type": "SBI PO Prelims"
    },
    {
      "correct_answer": "A",
      "options": [
        {
          "id": "A",
          "text": "25"
        },
        {
          "id": "B",
          "text": "20"
        },
        {
          "id": "C",
          "text": "35"
        },
        {
          "id": "D",
          "text": "38"
        }
      ],
      "question_number": 14,
      "question_text": "A trader sells an article at a profit of 16%; if he had sold it for ₹80 more, his profit would have been 48%. Find the number of articles sold, given that the total cost price is ₹8,000.",
      "exam_type": "Banking",
      "sub_type": "SBI PO Prelims"
    },
    {
      "correct_answer": "C",
      "options": [
        {
          "id": "A",
          "text": "205"
        },
        {
          "id": "B",
          "text": "210"
        },
        {
          "id": "C",
          "text": "200"
        },
        {
          "id": "D",
          "text": "205"
        }
      ],
      "question_number": 15,
      "question_text": "Subrata invested a certain amount of money at 10% per annum. After 2 years, he received ₹220.5 as compound interest, compounded annually. Find the corresponding simple interest (in ₹) for 2 years at the same rate.",
      "exam_type": "Banking",
      "sub_type": "SBI PO Prelims"
    },
    {
      "correct_answer": "A",
      "options": [
        {
          "id": "A",
          "text": "0"
        },
        {
          "id": "B",
          "text": "1"
        },
        {
          "id": "C",
          "text": "3"
        },
        {
          "id": "D",
          "text": "2"
        }
      ],
      "question_number": 16,
      "question_text": "Nisha noted the number 76488 in her register. What is the remainder when it is divided by 8?",
      "exam_type": "Banking",
      "sub_type": "SBI PO Prelims"
    },
    {
      "correct_answer": "C",
      "options": [
        {
          "id": "A",
          "text": "3661"
        },
        {
          "id": "B",
          "text": "3830"
        },
        {
          "id": "C",
          "text": "3840"
        },
        {
          "id": "D",
          "text": "3868"
        }
      ],
      "question_number": 17,
      "question_text": "Evaluate $20^3 + (-16)^3 + (-4)^3$",
      "exam_type": "Banking",
      "sub_type": "SBI PO Prelims"
    },
    {
      "correct_answer": "C",
      "options": [
        {
          "id": "A",
          "text": "30% loss"
        },
        {
          "id": "B",
          "text": "26% loss"
        },
        {
          "id": "C",
          "text": "30% profit"
        },
        {
          "id": "D",
          "text": "20% profit"
        }
      ],
      "question_number": 18,
      "question_text": "A shopkeeper buys sugar at ₹25 per kg. He marks it at ₹32 per kg and allows a 20% discount on the marked price. While selling, he uses an 800 g weight instead of 1 kg. What is his netither loss or expense. What is the overall profit or loss percentage of the shopkeeper?",
      "exam_type": "Banking",
      "sub_type": "SBI PO Prelims"
    },
    {
      "correct_answer": "D",
      "options": [
        {
          "id": "A",
          "text": "$8\\frac{1}{3}\\%$ decrease"
        },
        {
          "id": "B",
          "text": "$7\\frac{1}{7}\\%$ increase"
        },
        {
          "id": "C",
          "text": "$6\\frac{1}{3}\\%$ decrease"
        },
        {
          "id": "D",
          "text": "$8\\frac{1}{3}\\%$ increase"
        }
      ],
      "question_number": 19,
      "question_text": "A person spends 70% of his income. If his income increases by 20% and his expenditure increases by 25%, then find the percentage change in his savings.",
      "exam_type": "Banking",
      "sub_type": "SBI PO Prelims"
    },
    {
      "correct_answer": "C",
      "options": [
        {
          "id": "A",
          "text": "2 hours"
        },
        {
          "id": "B",
          "text": "5 hours"
        },
        {
          "id": "C",
          "text": "3 hours"
        },
        {
          "id": "D",
          "text": "4 hours"
        }
      ],
      "question_number": 20,
      "question_text": "The number of hours spent per day by 10 students watching educational videos during a week are as follows: 2, 3, 0, 4, 5, 4, 3, 2, 3, 1. Find the mode.",
      "exam_type": "Banking",
      "sub_type": "SBI PO Prelims"
    },
    {
      "correct_answer": "B",
      "options": [
        {
          "id": "A",
          "text": "B"
        },
        {
          "id": "B",
          "text": "C"
        },
        {
          "id": "C",
          "text": "D"
        },
        {
          "id": "D",
          "text": "A"
        }
      ],
      "question_number": 21,
      "question_text": "A shopkeeper offers the following schemes on toys of the same marked price. (A) Successive discounts of 30%, 20% and 10% on any number of toys bought. (B) Successive discounts of 42%, 38% and 20% on any number of toys bought. (C) 11% discount on the first 3 toys and 42% discount on each toy thereon. (D) Buy one get one free on buying 10 toys. A customer wants to buy 10 toys. Which of the above schemes is the least beneficial to her?",
      "exam_type": "Banking",
      "sub_type": "SBI PO Prelims"
    },
    {
      "correct_answer": "B",
      "options": [
        {
          "id": "A",
          "text": "18 minutes"
        },
        {
          "id": "B",
          "text": "24 minutes"
        },
        {
          "id": "C",
          "text": "14 minutes"
        },
        {
          "id": "D",
          "text": "34 minutes"
        }
      ],
      "question_number": 22,
      "question_text": "Inlet M fills a tank in 24 minutes and Inlet N fills it in 32 minutes. Outlet O drains the tank. If all three operate simultaneously, the tank fills in 12 minutes. How long does O take to drain a full tank alone?",
      "exam_type": "Banking",
      "sub_type": "SBI PO Prelims"
    },
    {
      "correct_answer": "A",
      "options": [
        {
          "id": "A",
          "text": "30.5"
        },
        {
          "id": "B",
          "text": "56.7"
        },
        {
          "id": "C",
          "text": "57.6"
        },
        {
          "id": "D",
          "text": "44.9"
        }
      ],
      "question_number": 23,
      "question_text": "At a health club, 42% of the members are women and 58% of the members are men. If the average age of the men is 37 years and the average age of the women is 22 years, what is the average age (in years) of all the members?",
      "exam_type": "Banking",
      "sub_type": "SBI PO Prelims"
    },
    {
      "correct_answer": "A",
      "options": [
        {
          "id": "A",
          "text": "45"
        },
        {
          "id": "B",
          "text": "50"
        },
        {
          "id": "C",
          "text": "65"
        },
        {
          "id": "D",
          "text": "25"
        }
      ],
      "question_number": 24,
      "question_text": "Simplify: $(\\sqrt{5} + \\sqrt{20})^2$",
      "exam_type": "Banking",
      "sub_type": "SBI PO Prelims"
    },
    {
      "correct_answer": "A",
      "options": [
        {
          "id": "A",
          "text": "10:1"
        },
        {
          "id": "B",
          "text": "7:1"
        },
        {
          "id": "C",
          "text": "5:2"
        },
        {
          "id": "D",
          "text": "7:1"
        }
      ],
      "question_number": 25,
      "question_text": "If the ratio of the number of boys to girls in a class is 5:7 and the ratio of girls to teachers is 14:1, what is the ratio of boys to teachers?",
      "exam_type": "Banking",
      "sub_type": "SBI PO Prelims"
    },
    {
      "correct_answer": "D",
      "options": [
        {
          "id": "A",
          "text": "14.2 seconds"
        },
        {
          "id": "B",
          "text": "12.61 seconds"
        },
        {
          "id": "C",
          "text": "15.43 seconds"
        },
        {
          "id": "D",
          "text": "13.71 seconds"
        }
      ],
      "question_number": 26,
      "question_text": "Two trains of equal lengths cross a stationary pole in 12 seconds and 16 seconds, respectively. How long will it take for the trains to cross each other when running in opposite directions? (Write your answer rounded off to two decimal places.)",
      "exam_type": "Banking",
      "sub_type": "SBI PO Prelims"
    },
    {
      "correct_answer": "B",
      "options": [
        {
          "id": "A",
          "text": "63.8 km/h"
        },
        {
          "id": "B",
          "text": "62.5 km/h"
        },
        {
          "id": "C",
          "text": "65.2 km/h"
        },
        {
          "id": "D",
          "text": "72.5 km/h"
        }
      ],
      "question_number": 27,
      "question_text": "The ratio between the speeds of two trains is 5:8. If the second train covers 300 km in 3 hours, then find the speed of the first train.",
      "exam_type": "Banking",
      "sub_type": "SBI PO Prelims"
    },
    {
      "correct_answer": "B",
      "options": [
        {
          "id": "A",
          "text": "72 m"
        },
        {
          "id": "B",
          "text": "18 m"
        },
        {
          "id": "C",
          "text": "36 m"
        },
        {
          "id": "D",
          "text": "12 m"
        }
      ],
      "question_number": 28,
      "question_text": "Three ropes of lengths 54 m, 72 m and 90 m are to be cut into smaller pieces of equal lengths such that no rope is left over. What is the maximum possible length of each smaller piece?",
      "exam_type": "Banking",
      "sub_type": "SBI PO Prelims"
    },
    {
      "correct_answer": "D",
      "options": [
        {
          "id": "A",
          "text": "8%"
        },
        {
          "id": "B",
          "text": "5%"
        },
        {
          "id": "C",
          "text": "12%"
        },
        {
          "id": "D",
          "text": "10%"
        }
      ],
      "question_number": 29,
      "question_text": "A jacket with a marked price of ₹2,000 is sold for ₹1,530 after two successive discounts. If the first discount is 15%, what is the second discount percentage?",
      "exam_type": "Banking",
      "sub_type": "SBI PO Prelims"
    },
    {
      "correct_answer": "D",
      "options": [
        {
          "id": "A",
          "text": "13.5"
        },
        {
          "id": "B",
          "text": "12.75"
        },
        {
          "id": "C",
          "text": "10.75"
        },
        {
          "id": "D",
          "text": "12.5"
        }
      ],
      "question_number": 30,
      "question_text": "If twice the smaller of two numbers is added to three times the larger number, the result is 55. If the larger is increased by 5, it becomes twice the smaller. What is the larger number?",
      "exam_type": "Banking",
      "sub_type": "SBI PO Prelims"
    },
    {
      "correct_answer": "C",
      "options": [
        {
          "id": "A",
          "text": "Hydraulic Energy"
        },
        {
          "id": "B",
          "text": "Chemical Energy"
        },
        {
          "id": "C",
          "text": "Kinetic Energy"
        },
        {
          "id": "D",
          "text": "Geothermal Energy"
        }
      ],
      "question_number": 31,
      "question_text": "When a stretched rubber band is released, its stored potential energy is converted into which form of energy?",
      "exam_type": "Banking",
      "sub_type": "SBI PO Prelims"
    },
    {
      "correct_answer": "A",
      "options": [
        {
          "id": "A",
          "text": "Tereza Fartes"
        },
        {
          "id": "B",
          "text": "Dr. Joseph Thi Ngoc Phuong"
        },
        {
          "id": "C",
          "text": "Hayao Miyazaki"
        },
        {
          "id": "D",
          "text": "Karma Phuntsho"
        }
      ],
      "question_number": 32,
      "question_text": "Who was the winner of the 2024 Ramon Magsaysay Award from Indonesia?",
      "exam_type": "Banking",
      "sub_type": "SBI PO Prelims"
    },
    {
      "correct_answer": "B",
      "options": [
        {
          "id": "A",
          "text": "Levees and meanders"
        },
        {
          "id": "B",
          "text": "Stalactites and stalagmites"
        },
        {
          "id": "C",
          "text": "Drumlins and eskers"
        },
        {
          "id": "D",
          "text": "Cirques and horns"
        }
      ],
      "question_number": 33,
      "question_text": "Which of the following pairs is formed inside limestone caves by deposition?",
      "exam_type": "Banking",
      "sub_type": "SBI PO Prelims"
    },
    {
      "correct_answer": "D",
      "options": [
        {
          "id": "A",
          "text": "Electronics Export Promotion Council (EEPC)"
        },
        {
          "id": "B",
          "text": "Small Industries Development Bank of India (SIDBI)"
        },
        {
          "id": "C",
          "text": "National Rural Livelihood Mission (NRLM)"
        },
        {
          "id": "D",
          "text": "National Bank for Agriculture and Rural Development (NABARD)"
        }
      ],
      "question_number": 34,
      "question_text": "Which national organisation jointly launched the \"Earth Summit 2025-26\" along with Internet and Mobile Association of India (IAMAI) to empower rural innovation?",
      "exam_type": "Banking",
      "sub_type": "SBI PO Prelims"
    },
    {
      "correct_answer": "D",
      "options": [
        {
          "id": "A",
          "text": "Intensive subsistence farming"
        },
        {
          "id": "B",
          "text": "Shifting cultivation"
        },
        {
          "id": "C",
          "text": "Plantation agriculture"
        },
        {
          "id": "D",
          "text": "Commercial grain farming"
        }
      ],
      "question_number": 35,
      "question_text": "Which type of agriculture is commonly practised in the wheat-producing regions of the USA and Canada?",
      "exam_type": "Banking",
      "sub_type": "SBI PO Prelims"
    },
    {
      "correct_answer": "A",
      "options": [
        {
          "id": "A",
          "text": "Samaveda"
        },
        {
          "id": "B",
          "text": "Atharvaveda"
        },
        {
          "id": "C",
          "text": "Rigveda"
        },
        {
          "id": "D",
          "text": "Yajurveda"
        }
      ],
      "question_number": 36,
      "question_text": "Which of the following Vedas is known as the 'Veda of Music'?",
      "exam_type": "Banking",
      "sub_type": "SBI PO Prelims"
    },
    {
      "correct_answer": "D",
      "options": [
        {
          "id": "A",
          "text": "Article 87"
        },
        {
          "id": "B",
          "text": "Article 79"
        },
        {
          "id": "C",
          "text": "Article 108"
        },
        {
          "id": "D",
          "text": "Article 85"
        }
      ],
      "question_number": 37,
      "question_text": "Under which article can the president summon, prorogue, or dissolve either house of Parliament?",
      "exam_type": "Banking",
      "sub_type": "SBI PO Prelims"
    },
    {
      "correct_answer": "D",
      "options": [
        {
          "id": "A",
          "text": "A committee formed by the President"
        },
        {
          "id": "B",
          "text": "A judicial panel of judges"
        },
        {
          "id": "C",
          "text": "A panel of civil servants"
        },
        {
          "id": "D",
          "text": "A panel of MPs selected by the Speaker"
        }
      ],
      "question_number": 38,
      "question_text": "Which of the following is a Parliamentary committee?",
      "exam_type": "Banking",
      "sub_type": "SBI PO Prelims"
    },
    {
      "correct_answer": "A",
      "options": [
        {
          "id": "A",
          "text": "Exfoliation"
        },
        {
          "id": "B",
          "text": "Carbonation"
        },
        {
          "id": "C",
          "text": "Salt crystallisation"
        },
        {
          "id": "D",
          "text": "Abrasion"
        }
      ],
      "question_number": 39,
      "question_text": "The peeling of curved sheets from massive rocks due to temperature changes is known as:",
      "exam_type": "Banking",
      "sub_type": "SBI PO Prelims"
    },
    {
      "correct_answer": "D",
      "options": [
        {
          "id": "A",
          "text": "Text paragraphs"
        },
        {
          "id": "B",
          "text": "Sound editing"
        },
        {
          "id": "C",
          "text": "Booting the computer"
        },
        {
          "id": "D",
          "text": "Spreadsheet data"
        }
      ],
      "question_number": 40,
      "question_text": "A \".xlsx\" file is created for:",
      "exam_type": "Banking",
      "sub_type": "SBI PO Prelims"
    },
    {
      "correct_answer": "B",
      "options": [
        {
          "id": "A",
          "text": "Diffusion"
        },
        {
          "id": "B",
          "text": "Osmosis"
        },
        {
          "id": "C",
          "text": "Plasymolysis"
        },
        {
          "id": "D",
          "text": "Active Transport"
        }
      ],
      "question_number": 41,
      "question_text": "The process by which water moves from the soil (high water concentration) into root cells (low water concentration) through a semi-permeable membrane is called _____.",
      "exam_type": "Banking",
      "sub_type": "SBI PO Prelims"
    },
    {
      "correct_answer": "B",
      "options": [
        {
          "id": "A",
          "text": "20%"
        },
        {
          "id": "B",
          "text": "12%"
        },
        {
          "id": "C",
          "text": "8%"
        },
        {
          "id": "D",
          "text": "10%"
        }
      ],
      "question_number": 42,
      "question_text": "By what percentage did rural poverty decline in India between 2005 and 2015 as a result of inclusive growth policies, according to the World Bank?",
      "exam_type": "Banking",
      "sub_type": "SBI PO Prelims"
    },
    {
      "correct_answer": "A",
      "options": [
        {
          "id": "A",
          "text": "Chandela"
        },
        {
          "id": "B",
          "text": "Rashtrakuta"
        },
        {
          "id": "C",
          "text": "Solanki"
        },
        {
          "id": "D",
          "text": "Gahadavala"
        }
      ],
      "question_number": 43,
      "question_text": "The Khajuraho group of temples was primarily built under which dynasty?",
      "exam_type": "Banking",
      "sub_type": "SBI PO Prelims"
    },
    {
      "correct_answer": "A",
      "options": [
        {
          "id": "A",
          "text": "Chambal"
        },
        {
          "id": "B",
          "text": "Ken"
        },
        {
          "id": "C",
          "text": "Ramganga"
        },
        {
          "id": "D",
          "text": "Gandak"
        }
      ],
      "question_number": 44,
      "question_text": "Which of the following Indian rivers is famous for its 'badland topography'?",
      "exam_type": "Banking",
      "sub_type": "SBI PO Prelims"
    },
    {
      "correct_answer": "B",
      "options": [
        {
          "id": "A",
          "text": "The spread of famines caused by failure in rice-growing regions."
        },
        {
          "id": "B",
          "text": "Transfer of tribal lands and intrusion of moneylenders and merchants."
        },
        {
          "id": "C",
          "text": "Ban on local festivals perceived as a threat to public order."
        },
        {
          "id": "D",
          "text": "Conscription of young men into British units for foreign service."
        }
      ],
      "question_number": 45,
      "question_text": "What prompted the Koi uprising in the Chhotanagpur region during 1831-32?",
      "exam_type": "Banking",
      "sub_type": "SBI PO Prelims"
    },
    {
      "correct_answer": "C",
      "options": [
        {
          "id": "A",
          "text": "Decreased slowly"
        },
        {
          "id": "B",
          "text": "Fluctuated unpredictably"
        },
        {
          "id": "C",
          "text": "Increased significantly"
        },
        {
          "id": "D",
          "text": "No change"
        }
      ],
      "question_number": 46,
      "question_text": "What effect did reforms have on India's GDP growth rate?",
      "exam_type": "Banking",
      "sub_type": "SBI PO Prelims"
    },
    {
      "correct_answer": "D",
      "options": [
        {
          "id": "A",
          "text": "Schedule XII"
        },
        {
          "id": "B",
          "text": "Schedule XI"
        },
        {
          "id": "C",
          "text": "Schedule IX"
        },
        {
          "id": "D",
          "text": "Schedule X"
        }
      ],
      "question_number": 47,
      "question_text": "Which of the following Schedules was added to the Constitution of India, to provide for the disqualification of the members of Parliament and the state legislatures on the ground of defection from one political party to another?",
      "exam_type": "Banking",
      "sub_type": "SBI PO Prelims"
    },
    {
      "correct_answer": "C",
      "options": [
        {
          "id": "A",
          "text": "Black Sea"
        },
        {
          "id": "B",
          "text": "Mediterranean Sea"
        },
        {
          "id": "C",
          "text": "Baltic Sea"
        },
        {
          "id": "D",
          "text": "North Sea"
        }
      ],
      "question_number": 48,
      "question_text": "Where did NATO announce increased military presence on January 18, 2025, following suspected sabotage of undersea infrastructure?",
      "exam_type": "Banking",
      "sub_type": "SBI PO Prelims"
    },
    {
      "correct_answer": "B",
      "options": [
        {
          "id": "A",
          "text": "Article 24"
        },
        {
          "id": "B",
          "text": "Article 26"
        },
        {
          "id": "C",
          "text": "Article 27"
        },
        {
          "id": "D",
          "text": "Article 23"
        }
      ],
      "question_number": 49,
      "question_text": "Which Article gives religious denominations the authority to conduct their religious affairs?",
      "exam_type": "Banking",
      "sub_type": "SBI PO Prelims"
    },
    {
      "correct_answer": "C",
      "options": [
        {
          "id": "A",
          "text": "Seventh"
        },
        {
          "id": "B",
          "text": "Sixth"
        },
        {
          "id": "C",
          "text": "Fifth"
        },
        {
          "id": "D",
          "text": "Third"
        }
      ],
      "question_number": 50,
      "question_text": "Which edition of the Khelo India University Games is being held in Rajasthan starting November 24, 2025?",
      "exam_type": "Banking",
      "sub_type": "SBI PO Prelims"
    },
    {
      "correct_answer": "D",
      "options": [
        {
          "id": "A",
          "text": "findstr"
        },
        {
          "id": "B",
          "text": "Tasklist"
        },
        {
          "id": "C",
          "text": "Ping"
        },
        {
          "id": "D",
          "text": "dir /s"
        }
      ],
      "question_number": 51,
      "question_text": "Which command-line tool is used in Windows to search for file names across directories without opening File Explorer?",
      "exam_type": "Banking",
      "sub_type": "SBI PO Prelims"
    },
    {
      "correct_answer": "A",
      "options": [
        {
          "id": "A",
          "text": "INS Shivalik"
        },
        {
          "id": "B",
          "text": "INS Sahyadri"
        },
        {
          "id": "C",
          "text": "INS Kolkata"
        },
        {
          "id": "D",
          "text": "INS Vikrant"
        }
      ],
      "question_number": 52,
      "question_text": "Which Indian naval ship is taking part in the Malabar exercise for the Quad Naval Drill in November 2025?",
      "exam_type": "Banking",
      "sub_type": "SBI PO Prelims"
    },
    {
      "correct_answer": "A",
      "options": [
        {
          "id": "A",
          "text": "Shah Mai"
        },
        {
          "id": "B",
          "text": "Gonoo Kol"
        },
        {
          "id": "C",
          "text": "Birjis Qadr"
        },
        {
          "id": "D",
          "text": "Nana Sahib"
        }
      ],
      "question_number": 53,
      "question_text": "During the revolt of 1857, the villagers of pargana Barout in Uttar Pradesh rallied under the leadership of which local figure?",
      "exam_type": "Banking",
      "sub_type": "SBI PO Prelims"
    },
    {
      "correct_answer": "B",
      "options": [
        {
          "id": "A",
          "text": "Gender equality today for a sustainable tomorrow"
        },
        {
          "id": "B",
          "text": "For All Women and Girls: Rights. Equality. Empowerment"
        },
        {
          "id": "C",
          "text": "DigitALL: Innovation and technology for gender equality"
        },
        {
          "id": "D",
          "text": "Invest in Women: Accelerate Progress"
        }
      ],
      "question_number": 54,
      "question_text": "What was the theme for International Women's Day 2025?",
      "exam_type": "Banking",
      "sub_type": "SBI PO Prelims"
    },
    {
      "correct_answer": "C",
      "options": [
        {
          "id": "A",
          "text": "Shows network connections for each app"
        },
        {
          "id": "B",
          "text": "Lists all installed applications"
        },
        {
          "id": "C",
          "text": "Manages which programs are allowed to start automatically when the user signs in"
        },
        {
          "id": "D",
          "text": "Displays system restore points"
        }
      ],
      "question_number": 55,
      "question_text": "What description best matches the purpose of the Startup apps tab in newer Windows Task Manager versions?",
      "exam_type": "Banking",
      "sub_type": "SBI PO Prelims"
    },
    {
      "correct_answer": "D",
      "options": [
        {
          "id": "A",
          "text": "Promotion of only domestic industries within national boundaries"
        },
        {
          "id": "B",
          "text": "Separation of national economies from global economic systems"
        },
        {
          "id": "C",
          "text": "Creation of worldwide socio-economic, social, and geopolitical boundaries"
        },
        {
          "id": "D",
          "text": "Reduction of international trade and cross-border economic linkages"
        }
      ],
      "question_number": 56,
      "question_text": "What is a key feature of globalisation?",
      "exam_type": "Banking",
      "sub_type": "SBI PO Prelims"
    },
    {
      "correct_answer": "B",
      "options": [
        {
          "id": "A",
          "text": "Reservation in promotions"
        },
        {
          "id": "B",
          "text": "Two Kerala Acts on land reforms"
        },
        {
          "id": "C",
          "text": "Environmental protection laws"
        },
        {
          "id": "D",
          "text": "Special provisions for Mizoram"
        }
      ],
      "question_number": 57,
      "question_text": "The Seventh Ninth Amendment Act of 1972 included which of the following in the Ninth Schedule?",
      "exam_type": "Banking",
      "sub_type": "SBI PO Prelims"
    },
    {
      "correct_answer": "A",
      "options": [
        {
          "id": "A",
          "text": "A compositional lyric form"
        },
        {
          "id": "B",
          "text": "A melodic scales in music"
        },
        {
          "id": "C",
          "text": "A type of physical instrumentation"
        },
        {
          "id": "D",
          "text": "A rhythmic pattern"
        }
      ],
      "question_number": 58,
      "question_text": "The term 'Kriti' in Carnatic music refers to:",
      "exam_type": "Banking",
      "sub_type": "SBI PO Prelims"
    },
    {
      "correct_answer": "B",
      "options": [
        {
          "id": "A",
          "text": "Gwalior"
        },
        {
          "id": "B",
          "text": "Chausa"
        },
        {
          "id": "C",
          "text": "Kannauj"
        },
        {
          "id": "D",
          "text": "Panipat"
        }
      ],
      "question_number": 59,
      "question_text": "At which place did Sher Shah first defeat Humayun in 1539?",
      "exam_type": "Banking",
      "sub_type": "SBI PO Prelims"
    },
    {
      "correct_answer": "C",
      "options": [
        {
          "id": "A",
          "text": "Uttar Pradesh"
        },
        {
          "id": "B",
          "text": "West Bengal"
        },
        {
          "id": "C",
          "text": "Odisha"
        },
        {
          "id": "D",
          "text": "Gujarat"
        }
      ],
      "question_number": 60,
      "question_text": "Rangabati is a famous folk dance from which of the following states of India?",
      "exam_type": "Banking",
      "sub_type": "SBI PO Prelims"
    },
    {
      "correct_answer": "B",
      "options": [
        {
          "id": "A",
          "text": "River valleys, floodplains, health clinics"
        },
        {
          "id": "B",
          "text": "Harsh climate, poor soil, few roads"
        },
        {
          "id": "C",
          "text": "Mild winters, abundant water, schools"
        },
        {
          "id": "D",
          "text": "Flat terrain, fertile soil, urban jobs"
        }
      ],
      "question_number": 61,
      "question_text": "Which one of the following combinations contributes to low population density?",
      "exam_type": "Banking",
      "sub_type": "SBI PO Prelims"
    },
    {
      "correct_answer": "A",
      "options": [
        {
          "id": "A",
          "text": "Modi tunnel"
        },
        {
          "id": "B",
          "text": "Pir Panjal tunnel"
        },
        {
          "id": "C",
          "text": "Atal tunnel"
        },
        {
          "id": "D",
          "text": "Nehru tunnel"
        }
      ],
      "question_number": 62,
      "question_text": "Which of the following tunnels has been inaugurated in January 2026 to improve year-round connectivity between Sonamarg and Srinagar?",
      "exam_type": "Banking",
      "sub_type": "SBI PO Prelims"
    },
    {
      "correct_answer": "C",
      "options": [
        {
          "id": "A",
          "text": "IEEE 802.16"
        },
        {
          "id": "B",
          "text": "IEEE 802.11"
        },
        {
          "id": "C",
          "text": "IEEE 802.3"
        },
        {
          "id": "D",
          "text": "IEEE 802.15"
        }
      ],
      "question_number": 63,
      "question_text": "Which standard is commonly used for wired LANs?",
      "exam_type": "Banking",
      "sub_type": "SBI PO Prelims"
    },
    {
      "correct_answer": "D",
      "options": [
        {
          "id": "A",
          "text": "Law of periodicity"
        },
        {
          "id": "B",
          "text": "Law of definite proportions"
        },
        {
          "id": "C",
          "text": "Law of Definite Composition"
        },
        {
          "id": "D",
          "text": "Law of Conservation of Mass"
        }
      ],
      "question_number": 64,
      "question_text": "Which of the following explains that during a chemical reaction, the sum of masses of the reactants and products remains unchanged?",
      "exam_type": "Banking",
      "sub_type": "SBI PO Prelims"
    },
    {
      "correct_answer": "B",
      "options": [
        {
          "id": "A",
          "text": "Yashodharman"
        },
        {
          "id": "B",
          "text": "Durlabhavardhana"
        },
        {
          "id": "C",
          "text": "Harshavardhana"
        },
        {
          "id": "D",
          "text": "Pulakeshin II"
        }
      ],
      "question_number": 65,
      "question_text": "The Chinese pilgrim Xuanzang (Hiuen Tsang) visited Kashmir during the reign of:",
      "exam_type": "Banking",
      "sub_type": "SBI PO Prelims"
    },
    {
      "correct_answer": "D",
      "options": [
        {
          "id": "A",
          "text": "Withdrawing British forces from major towns to avoid further confrontation."
        },
        {
          "id": "B",
          "text": "Allowing the Mughal emperor to govern Delhi under strict British supervision."
        },
        {
          "id": "C",
          "text": "Negotiating a settlement that restored regional rulers to their former positions."
        },
        {
          "id": "D",
          "text": "Recapturing key centres, enacting new laws, and offering rewards to loyal chiefs."
        }
      ],
      "question_number": 66,
      "question_text": "Which strategy was used by the British to regain control after initial rebel victories across northern India in the Revolt of 1857?",
      "exam_type": "Banking",
      "sub_type": "SBI PO Prelims"
    },
    {
      "correct_answer": "B",
      "options": [
        {
          "id": "A",
          "text": "Article 243-ZC"
        },
        {
          "id": "B",
          "text": "Article 243-W"
        },
        {
          "id": "C",
          "text": "Article 243-P"
        },
        {
          "id": "D",
          "text": "Article 243-Q"
        }
      ],
      "question_number": 67,
      "question_text": "Which Article authorises municipalities to perform Twelfth Schedule functions introduced through this Constitutional Amendment Act?",
      "exam_type": "Banking",
      "sub_type": "SBI PO Prelims"
    },
    {
      "correct_answer": "B",
      "options": [
        {
          "id": "A",
          "text": "A double displacement reaction forms iron sulphate and copper sulphate"
        },
        {
          "id": "B",
          "text": "A displacement reaction occurs, forming copper metal on the iron nails"
        },
        {
          "id": "C",
          "text": "A decomposition reaction occurs, breaking copper sulphate into $\\text{SO}_2$ and copper"
        },
        {
          "id": "D",
          "text": "A combination reaction occurs, creating iron sulphate crystals"
        }
      ],
      "question_number": 68,
      "question_text": "During an experiment, iron nails are placed in copper sulphate solution, and a reddish-brown deposit forms on the nails. What does this observation demonstrate about the type of chemical reaction that the substances involved?",
      "exam_type": "Banking",
      "sub_type": "SBI PO Prelims"
    },
    {
      "correct_answer": "D",
      "options": [
        {
          "id": "A",
          "text": "Amitabh Bachchan"
        },
        {
          "id": "B",
          "text": "Madhuri"
        },
        {
          "id": "C",
          "text": "Hrithik Roshan"
        },
        {
          "id": "D",
          "text": "Akshay Kumar"
        }
      ],
      "question_number": 69,
      "question_text": "Who received the Chief of Army Staff Commendation Card from General Upendra Dwivedi on October 7, 2025?",
      "exam_type": "Banking",
      "sub_type": "SBI PO Prelims"
    },
    {
      "correct_answer": "A",
      "options": [
        {
          "id": "A",
          "text": "Tertiary"
        },
        {
          "id": "B",
          "text": "Primary"
        },
        {
          "id": "C",
          "text": "Secondary"
        },
        {
          "id": "D",
          "text": "Quinary"
        }
      ],
      "question_number": 70,
      "question_text": "Which of the following sectors includes activities like trade, transport, and communication in India?",
      "exam_type": "Banking",
      "sub_type": "SBI PO Prelims"
    },
    {
      "correct_answer": "C",
      "options": [
        {
          "id": "A",
          "text": "68"
        },
        {
          "id": "B",
          "text": "62"
        },
        {
          "id": "C",
          "text": "64"
        },
        {
          "id": "D",
          "text": "60"
        }
      ],
      "question_number": 71,
      "question_text": "What should come in place of '?' in the given series? 4, 8, 12, 16, 28, 32, ?",
      "exam_type": "Banking",
      "sub_type": "SBI PO Prelims"
    },
    {
      "correct_answer": "B",
      "options": [
        {
          "id": "A",
          "text": "8"
        },
        {
          "id": "B",
          "text": "8"
        },
        {
          "id": "C",
          "text": "5"
        },
        {
          "id": "D",
          "text": "7"
        }
      ],
      "question_number": 72,
      "question_text": "If 'A' stands for '-', 'B' stands for '$\\times$', 'C' stands for '+' and 'D' stands for '$\\div$', then what will come in place of the question mark (?) in the following equation? $1 \\text{ D } 40 \\text{ A } 7 \\text{ B } 7 \\text{ C } 46 = ?$",
      "exam_type": "Banking",
      "sub_type": "SBI PO Prelims"
    },
    {
      "correct_answer": "B",
      "options": [
        {
          "id": "A",
          "text": "JNR"
        },
        {
          "id": "B",
          "text": "TNP"
        },
        {
          "id": "C",
          "text": "SWY"
        },
        {
          "id": "D",
          "text": "OJO"
        }
      ],
      "question_number": 73,
      "question_text": "Based on the alphabetical order, three of the following four are alike in a certain way and thus form a group. Which is the one that does not belong to that group? (Note: The odd man out is not based on the number of consonants/vowels or their position in the letter cluster.)",
      "exam_type": "Banking",
      "sub_type": "SBI PO Prelims"
    },
    {
      "correct_answer": "D",
      "options": [
        {
          "id": "A",
          "text": "MKI"
        },
        {
          "id": "B",
          "text": "QQM"
        },
        {
          "id": "C",
          "text": "CBY"
        },
        {
          "id": "D",
          "text": "BZX"
        }
      ],
      "question_number": 74,
      "question_text": "Based on the English alphabetical order, three of the following four are alike in a certain way and thus form a group. Which is the one that does not belong to that group? (Note: The odd man out is not based on the number of consonants/vowels or their position in the letter cluster.)",
      "exam_type": "Banking",
      "sub_type": "SBI PO Prelims"
    },
    {
      "correct_answer": "D",
      "options": [
        {
          "id": "A",
          "text": "IDA 64"
        },
        {
          "id": "B",
          "text": "KLA 64"
        },
        {
          "id": "C",
          "text": "PCB 65"
        },
        {
          "id": "D",
          "text": "IFA 65"
        }
      ],
      "question_number": 75,
      "question_text": "Which of the following letter-number clusters will replace the question mark (?) in the given series to make it logically complete? DKH 41, GCZ 47, YUR 53, QMJ 59, ?",
      "exam_type": "Banking",
      "sub_type": "SBI PO Prelims"
    },
    {
      "correct_answer": "A",
      "options": [
        {
          "id": "A",
          "text": "171"
        },
        {
          "id": "B",
          "text": "169"
        },
        {
          "id": "C",
          "text": "175"
        },
        {
          "id": "D",
          "text": "166"
        }
      ],
      "question_number": 76,
      "question_text": "What should come in place of '?' in the given series? 10 19 36 68 123 ?",
      "exam_type": "Banking",
      "sub_type": "SBI PO Prelims"
    },
    {
      "correct_answer": "B",
      "options": [
        {
          "id": "A",
          "text": "BOBY"
        },
        {
          "id": "B",
          "text": "BYOB"
        },
        {
          "id": "C",
          "text": "BOYB"
        },
        {
          "id": "D",
          "text": "BBOY"
        }
      ],
      "question_number": 77,
      "question_text": "FACN is related to LFIS in a certain way based on the English alphabetical order. In the same way, DUAH is related to JZGM. To which of the following options is VJSW related, following the same logic?",
      "exam_type": "Banking",
      "sub_type": "SBI PO Prelims"
    },
    {
      "correct_answer": "D",
      "options": [
        {
          "id": "A",
          "text": "34"
        },
        {
          "id": "B",
          "text": "20"
        },
        {
          "id": "C",
          "text": "28"
        },
        {
          "id": "D",
          "text": "48"
        }
      ],
      "question_number": 78,
      "question_text": "If 'P' stands for '+', 'Q' stands for '$\\times$', 'R' stands for '-' and 'S' stands for '$\\div$', what will come in place of the question mark (?) in the following equation? $(96 \\text{ S } 12) \\text{ P } 5 \\text{ (42 Q 7) } \\text{ P } 18 \\text{ R } 12 \\text{ P } 5 = ?$",
      "exam_type": "Banking",
      "sub_type": "SBI PO Prelims"
    },
    {
      "correct_answer": "A",
      "options": [
        {
          "id": "A",
          "text": "BDB 57"
        },
        {
          "id": "B",
          "text": "BFK 56"
        },
        {
          "id": "C",
          "text": "BEA 57"
        },
        {
          "id": "D",
          "text": "BCA 56"
        }
      ],
      "question_number": 79,
      "question_text": "Which of the following letter-number clusters will replace the question mark (?) in the given series to make it logically complete? RTR 77 NPN 72 JLJ 67 FR 62 ?",
      "exam_type": "Banking",
      "sub_type": "SBI PO Prelims"
    },
    {
      "correct_answer": "D",
      "options": [
        {
          "id": "A",
          "text": "90"
        },
        {
          "id": "B",
          "text": "93"
        },
        {
          "id": "C",
          "text": "92"
        },
        {
          "id": "D",
          "text": "91"
        }
      ],
      "question_number": 80,
      "question_text": "Raman ranked 25th from the top and 67th from the bottom in his class. How many students were there in his class?",
      "exam_type": "Banking",
      "sub_type": "SBI PO Prelims"
    },
    {
      "correct_answer": "B",
      "options": [
        {
          "id": "A",
          "text": "3 and 7"
        },
        {
          "id": "B",
          "text": "5 and 6"
        },
        {
          "id": "C",
          "text": "36 and 21"
        },
        {
          "id": "D",
          "text": "4 and 5"
        }
      ],
      "question_number": 81,
      "question_text": "Which two numbers should be interchanged to make the given equation correct? $(21 + 2) \\times 3 + 15 \\times 5 - 19 \\times 4 + 36 + 7 \\times 6 = 57$",
      "exam_type": "Banking",
      "sub_type": "SBI PO Prelims"
    },
    {
      "correct_answer": "D",
      "options": [
        {
          "id": "A",
          "text": "B"
        },
        {
          "id": "B",
          "text": "D"
        },
        {
          "id": "C",
          "text": "G"
        },
        {
          "id": "D",
          "text": "C"
        }
      ],
      "question_number": 82,
      "question_text": "Seven people A, B, C, D, E, F and G are sitting around a circular table facing towards the centre of the table. E sits second to the left of A. G is sitting immediately between B and C. D sits to the immediate right of C. Who is sitting immediately between E and F?",
      "exam_type": "Banking",
      "sub_type": "SBI PO Prelims"
    },
    {
      "correct_answer": "B",
      "options": [
        {
          "id": "A",
          "text": "1"
        },
        {
          "id": "B",
          "text": "4"
        },
        {
          "id": "C",
          "text": "7"
        },
        {
          "id": "D",
          "text": "2"
        }
      ],
      "question_number": 83,
      "question_text": "In a certain code language, 'SOAP' is coded as '5279' and 'ATOP' is coded as '4527'. What is the code for 'T' in the given code language?",
      "exam_type": "Banking",
      "sub_type": "SBI PO Prelims"
    },
    {
      "correct_answer": "D",
      "options": [
        {
          "id": "A",
          "text": "One"
        },
        {
          "id": "B",
          "text": "None"
        },
        {
          "id": "C",
          "text": "More than two"
        },
        {
          "id": "D",
          "text": "Two"
        }
      ],
      "question_number": 84,
      "question_text": "Refer to the following series and answer the question. (Counting to be done from left to right only.) (All numbers are single-digit numbers only.) L # H 6 & S 4 U @ 9 % G 1 A T 2 $ P 5 Q W E R 3 Z (Right) How many such odd digits are there, each of which is immediately preceded by an even digit and also immediately followed by an odd digit?",
      "exam_type": "Banking",
      "sub_type": "SBI PO Prelims"
    },
    {
      "correct_answer": "D",
      "options": [
        {
          "id": "A",
          "text": "Three"
        },
        {
          "id": "B",
          "text": "Two"
        },
        {
          "id": "C",
          "text": "None"
        },
        {
          "id": "D",
          "text": "One"
        }
      ],
      "question_number": 85,
      "question_text": "Refer to the following letter series and answer the question. Counting to be done from left to right only. (B) U N C J W Q X P E L Q R C G R U A Z R U (Right) How many such vowels are there, each of which is immediately preceded by a vowel and also immediately followed by a consonant?",
      "exam_type": "Banking",
      "sub_type": "SBI PO Prelims"
    },
    {
      "correct_answer": "D",
      "options": [
        {
          "id": "A",
          "text": "WEAR - WAER - RAEW"
        },
        {
          "id": "B",
          "text": "POND - OPND - DONP"
        },
        {
          "id": "C",
          "text": "KITE - IETK - ETIK"
        },
        {
          "id": "D",
          "text": "LEGS - ELGS - SEGL"
        }
      ],
      "question_number": 86,
      "question_text": "In the following triad, each group of letters is related to the subsequent one following a certain logic. Select, from the given options, the one which follows the same logic. MNQA - OQPM - SQRM TONG - QSNT - WNOT",
      "exam_type": "Banking",
      "sub_type": "SBI PO Prelims"
    },
    {
      "correct_answer": "B",
      "options": [
        {
          "id": "A",
          "text": "Q"
        },
        {
          "id": "B",
          "text": "R"
        },
        {
          "id": "C",
          "text": "O"
        },
        {
          "id": "D",
          "text": "S"
        }
      ],
      "question_number": 87,
      "question_text": "Seven boxes M, N, O, P, Q, R and S, are kept one over the other, but not necessarily in the same order. N is kept fourth from the top. Only two boxes are kept between N and S. Only P is kept above M, but not immediately above M. O is kept on one of the positions after M but on one of the positions before R. Which box is kept fourth from the bottom?",
      "exam_type": "Banking",
      "sub_type": "SBI PO Prelims"
    },
    {
      "correct_answer": "D",
      "options": [
        {
          "id": "A",
          "text": "3"
        },
        {
          "id": "B",
          "text": "9"
        },
        {
          "id": "C",
          "text": "8"
        },
        {
          "id": "D",
          "text": "6"
        }
      ],
      "question_number": 88,
      "question_text": "In a certain code language, 'SAFE' is coded as '3698' and 'FACE' is coded as '5398'. What is the code for 'D' in the given code language?",
      "exam_type": "Banking",
      "sub_type": "SBI PO Prelims"
    },
    {
      "correct_answer": "B",
      "options": [
        {
          "id": "A",
          "text": "Both conclusions (I) and (II) follow"
        },
        {
          "id": "B",
          "text": "Only conclusion (I) follows"
        },
        {
          "id": "C",
          "text": "Neither conclusion (I) nor (II) follows"
        },
        {
          "id": "D",
          "text": "Only conclusion (II) follows"
        }
      ],
      "question_number": 89,
      "question_text": "Read the given statements and conclusions carefully. Assuming that the information given in the statements is true, even if it appears to be at variance with commonly known facts, decide which of the given conclusions logically follow(s) from the statements. Statements: I: All Cobalt is Silver. II: No Silver is Vanadium. Conclusion I: No Vanadium is Cobalt. Conclusion II: Some Vanadium is Cobalt.",
      "exam_type": "Banking",
      "sub_type": "SBI PO Prelims"
    },
    {
      "correct_answer": "D",
      "options": [
        {
          "id": "A",
          "text": "78 km towards East"
        },
        {
          "id": "B",
          "text": "75 km towards west"
        },
        {
          "id": "C",
          "text": "71 km towards west"
        },
        {
          "id": "D",
          "text": "71 km towards east"
        }
      ],
      "question_number": 90,
      "question_text": "Tanmay starts from Point Y and drives 23 km towards West. He then takes a right turn, drives 31 km, again drives 40 km. He then takes a right turn and drives 24 km. He takes a right turn, drives 79 km. He then turns left, drives 36 km to stop at Point Z. How far and in which direction is Tanmay from Point Y? (Assume all turns are $90^\\circ$ turns only unless specified.)",
      "exam_type": "Banking",
      "sub_type": "SBI PO Prelims"
    },
    {
      "correct_answer": "C",
      "options": [
        {
          "id": "A",
          "text": "TW7"
        },
        {
          "id": "B",
          "text": "SV1"
        },
        {
          "id": "C",
          "text": "TV1"
        },
        {
          "id": "D",
          "text": "TV8"
        }
      ],
      "question_number": 91,
      "question_text": "Which of the following letter-number clusters will replace the question mark (?) in the given series to make it logically complete? KE64, MC27, PZ8, ?",
      "exam_type": "Banking",
      "sub_type": "SBI PO Prelims"
    },
    {
      "correct_answer": "D",
      "options": [
        {
          "id": "A",
          "text": "(21, 206, 194)"
        },
        {
          "id": "B",
          "text": "(74, 68, 55)"
        },
        {
          "id": "C",
          "text": "(33, 27, 14)"
        },
        {
          "id": "D",
          "text": "(85, 76, 64)"
        }
      ],
      "question_number": 92,
      "question_text": "Select the set in which the numbers are related in the same way as are the numbers of the following sets. (NOTE: Operations should be performed on the whole numbers, without breaking down the numbers into their constituent digits. E.g. 13 can be operated on as 13 and not as 1 and 3. Breaking down 13 into 1 and 3 and then performing mathematical operations on 1 and 3 is not allowed.) (63, 47, 35) (117, 101, 89)",
      "exam_type": "Banking",
      "sub_type": "SBI PO Prelims"
    },
    {
      "correct_answer": "A",
      "options": [
        {
          "id": "A",
          "text": "Neither conclusion (I) nor (II) follow"
        },
        {
          "id": "B",
          "text": "Both conclusions (I) and (II) follow"
        },
        {
          "id": "C",
          "text": "Only conclusion (I) follows"
        },
        {
          "id": "D",
          "text": "Only conclusion (II) follows"
        }
      ],
      "question_number": 93,
      "question_text": "Read the given statement(s) and conclusions carefully. Assuming that the information given in the statements is true, even if it appears to be at variance with commonly known facts, decide which of the given conclusions logically follow(s) from the statement(s). Statements: Some phones are irons. Some irons are vaults. Conclusions (I): No iron is a phone. Conclusions (II): Some phones are vaults.",
      "exam_type": "Banking",
      "sub_type": "SBI PO Prelims"
    },
    {
      "correct_answer": "D",
      "options": [
        {
          "id": "A",
          "text": "H"
        },
        {
          "id": "B",
          "text": "K"
        },
        {
          "id": "C",
          "text": "G"
        },
        {
          "id": "D",
          "text": "L"
        }
      ],
      "question_number": 94,
      "question_text": "Seven boxes, G, H, I, J, K, L and M, are kept one over the other, but not necessarily in the same order. Only three boxes are kept between M and J. I is kept third from the top. Only M is kept below I. Only one box is kept between J. G is kept at one of the positions below M but not immediately above J. Which box is kept third from the bottom?",
      "exam_type": "Banking",
      "sub_type": "SBI PO Prelims"
    },
    {
      "correct_answer": "B",
      "options": [
        {
          "id": "A",
          "text": "RCQ"
        },
        {
          "id": "B",
          "text": "XUY"
        },
        {
          "id": "C",
          "text": "NKO"
        },
        {
          "id": "D",
          "text": "LJM"
        }
      ],
      "question_number": 95,
      "question_text": "Based on the alphabetical order, three of the following four are alike in a certain way and thus form a group. Which is the one that does not belong to that group? (Note: The odd man out is not based on the number of consonants/vowels or their position in the letter cluster.)",
      "exam_type": "Banking",
      "sub_type": "SBI PO Prelims"
    },
    {
      "correct_answer": "C",
      "options": [
        {
          "id": "A",
          "text": "JZ -12"
        },
        {
          "id": "B",
          "text": "KL -10"
        },
        {
          "id": "C",
          "text": "NG -11"
        },
        {
          "id": "D",
          "text": "HY -9"
        }
      ],
      "question_number": 96,
      "question_text": "SF 19 is related to VA 6 in a certain way. In the same way, GG 16 is related to JB 3. To which of the following is KL 2 related, following the same logic?",
      "exam_type": "Banking",
      "sub_type": "SBI PO Prelims"
    },
    {
      "correct_answer": "D",
      "options": [
        {
          "id": "A",
          "text": "Four"
        },
        {
          "id": "B",
          "text": "Three"
        },
        {
          "id": "C",
          "text": "One"
        },
        {
          "id": "D",
          "text": "Two"
        }
      ],
      "question_number": 97,
      "question_text": "Seven people, U, T, E, N, S, I and L, are sitting in a row, facing the north. Only two people sit to the left of N. Only three people sit between N and S. Only one person sits between S and E. I sits to the immediate left of L. U is not an immediate neighbour of N. How many people sit to the right of T?",
      "exam_type": "Banking",
      "sub_type": "SBI PO Prelims"
    },
    {
      "correct_answer": "A",
      "options": [
        {
          "id": "A",
          "text": "Daughter's husband"
        },
        {
          "id": "B",
          "text": "Father"
        },
        {
          "id": "C",
          "text": "Brother"
        },
        {
          "id": "D",
          "text": "Daughter's son"
        }
      ],
      "question_number": 98,
      "question_text": "G is the father of Y. Y is the brother of J. M is the father of W. W is the son of J. How is M related to G?",
      "exam_type": "Banking",
      "sub_type": "SBI PO Prelims"
    },
    {
      "correct_answer": "D",
      "options": [
        {
          "id": "A",
          "text": "15"
        },
        {
          "id": "B",
          "text": "17"
        },
        {
          "id": "C",
          "text": "14"
        },
        {
          "id": "D",
          "text": "13"
        }
      ],
      "question_number": 99,
      "question_text": "Each letter in the word HARMFUL is arranged in the English alphabetical order. How many letters are there in the English alphabetical order between the letter which is second from the left and the one which is first from the right in the new letter cluster thus formed?",
      "exam_type": "Banking",
      "sub_type": "SBI PO Prelims"
    },
    {
      "correct_answer": "D",
      "options": [
        {
          "id": "A",
          "text": "Mother's father"
        },
        {
          "id": "B",
          "text": "Mother's father"
        },
        {
          "id": "C",
          "text": "Mother's daughter"
        },
        {
          "id": "D",
          "text": "Mother's sister"
        }
      ],
      "question_number": 100,
      "question_text": "In a certain code language, 'A @ B means 'A is the wife of B', 'A # B means 'A is the mother of B', 'A % B means 'A is the father of B' and 'A + B means 'A is the daughter of B'. How is M related to H if 'M + A @ R ? C ; H'?",
      "exam_type": "Banking",
      "sub_type": "SBI PO Prelims"
    }
  ]
}